<?xml version="1.0" encoding="UTF-8"?>
<dia:diagram xmlns:dia="http://www.lysator.liu.se/~alla/dia/">
  <dia:diagramdata>
    <dia:attribute name="background">
      <dia:color val="#ffffff"/>
    </dia:attribute>
    <dia:attribute name="pagebreak">
      <dia:color val="#000099"/>
    </dia:attribute>
    <dia:attribute name="paper">
      <dia:composite type="paper">
        <dia:attribute name="name">
          <dia:string>#A4#</dia:string>
        </dia:attribute>
        <dia:attribute name="tmargin">
          <dia:real val="2.8222000598907471"/>
        </dia:attribute>
        <dia:attribute name="bmargin">
          <dia:real val="2.8222000598907471"/>
        </dia:attribute>
        <dia:attribute name="lmargin">
          <dia:real val="2.8222000598907471"/>
        </dia:attribute>
        <dia:attribute name="rmargin">
          <dia:real val="2.8222000598907471"/>
        </dia:attribute>
        <dia:attribute name="is_portrait">
          <dia:boolean val="true"/>
        </dia:attribute>
        <dia:attribute name="scaling">
          <dia:real val="1"/>
        </dia:attribute>
        <dia:attribute name="fitto">
          <dia:boolean val="false"/>
        </dia:attribute>
      </dia:composite>
    </dia:attribute>
    <dia:attribute name="grid">
      <dia:composite type="grid">
        <dia:attribute name="width_x">
          <dia:real val="1"/>
        </dia:attribute>
        <dia:attribute name="width_y">
          <dia:real val="1"/>
        </dia:attribute>
        <dia:attribute name="visible_x">
          <dia:int val="1"/>
        </dia:attribute>
        <dia:attribute name="visible_y">
          <dia:int val="1"/>
        </dia:attribute>
        <dia:composite type="color"/>
      </dia:composite>
    </dia:attribute>
    <dia:attribute name="color">
      <dia:color val="#d8e5e5"/>
    </dia:attribute>
    <dia:attribute name="guides">
      <dia:composite type="guides">
        <dia:attribute name="hguides"/>
        <dia:attribute name="vguides"/>
      </dia:composite>
    </dia:attribute>
  </dia:diagramdata>
  <dia:layer name="Background" visible="true">
    <dia:object type="Standard - Box" version="0" id="O0">
      <dia:attribute name="obj_pos">
        <dia:point val="5.92447,17.7174"/>
      </dia:attribute>
      <dia:attribute name="obj_bb">
        <dia:rectangle val="5.89947,17.6924;12.4163,20.8414"/>
      </dia:attribute>
      <dia:attribute name="elem_corner">
        <dia:point val="5.92447,17.7174"/>
      </dia:attribute>
      <dia:attribute name="elem_width">
        <dia:real val="6.466843888531665"/>
      </dia:attribute>
      <dia:attribute name="elem_height">
        <dia:real val="3.0990282000876377"/>
      </dia:attribute>
      <dia:attribute name="border_width">
        <dia:real val="0.050000000000000003"/>
      </dia:attribute>
      <dia:attribute name="inner_color">
        <dia:color val="#dcfff7"/>
      </dia:attribute>
      <dia:attribute name="show_background">
        <dia:boolean val="true"/>
      </dia:attribute>
      <dia:attribute name="line_style">
        <dia:enum val="4"/>
      </dia:attribute>
      <dia:attribute name="dashlength">
        <dia:real val="0.5"/>
      </dia:attribute>
      <dia:attribute name="corner_radius">
        <dia:real val="0.5"/>
      </dia:attribute>
    </dia:object>
    <dia:object type="Standard - Box" version="0" id="O1">
      <dia:attribute name="obj_pos">
        <dia:point val="1.06631,4.01038"/>
      </dia:attribute>
      <dia:attribute name="obj_bb">
        <dia:rectangle val="1.04131,3.98538;12.4388,17.3658"/>
      </dia:attribute>
      <dia:attribute name="elem_corner">
        <dia:point val="1.06631,4.01038"/>
      </dia:attribute>
      <dia:attribute name="elem_width">
        <dia:real val="11.3475179991236"/>
      </dia:attribute>
      <dia:attribute name="elem_height">
        <dia:real val="13.330389999999996"/>
      </dia:attribute>
      <dia:attribute name="border_width">
        <dia:real val="0.050000000000000003"/>
      </dia:attribute>
      <dia:attribute name="inner_color">
        <dia:color val="#f9ffa9"/>
      </dia:attribute>
      <dia:attribute name="show_background">
        <dia:boolean val="true"/>
      </dia:attribute>
      <dia:attribute name="line_style">
        <dia:enum val="4"/>
      </dia:attribute>
      <dia:attribute name="dashlength">
        <dia:real val="0.5"/>
      </dia:attribute>
      <dia:attribute name="corner_radius">
        <dia:real val="0.5"/>
      </dia:attribute>
    </dia:object>
    <dia:object type="Standard - Line" version="0" id="O2">
      <dia:attribute name="obj_pos">
        <dia:point val="8.7201,8.35877"/>
      </dia:attribute>
      <dia:attribute name="obj_bb">
        <dia:rectangle val="8.46687,8.10554;10.8983,8.637"/>
      </dia:attribute>
      <dia:attribute name="conn_endpoints">
        <dia:point val="8.7201,8.35877"/>
        <dia:point val="10.6451,8.38377"/>
      </dia:attribute>
      <dia:attribute name="numcp">
        <dia:int val="1"/>
      </dia:attribute>
      <dia:attribute name="line_color">
        <dia:color val="#bfbfbf"/>
      </dia:attribute>
      <dia:attribute name="line_width">
        <dia:real val="0.5"/>
      </dia:attribute>
    </dia:object>
    <dia:object type="Standard - Line" version="0" id="O3">
      <dia:attribute name="obj_pos">
        <dia:point val="4.79131,9.00275"/>
      </dia:attribute>
      <dia:attribute name="obj_bb">
        <dia:rectangle val="4.54037,8.75181;5.05094,11.5597"/>
      </dia:attribute>
      <dia:attribute name="conn_endpoints">
        <dia:point val="4.79131,9.00275"/>
        <dia:point val="4.8,11.3088"/>
      </dia:attribute>
      <dia:attribute name="numcp">
        <dia:int val="1"/>
      </dia:attribute>
      <dia:attribute name="line_color">
        <dia:color val="#bfbfbf"/>
      </dia:attribute>
      <dia:attribute name="line_width">
        <dia:real val="0.5"/>
      </dia:attribute>
    </dia:object>
    <dia:object type="Standard - Line" version="0" id="O4">
      <dia:attribute name="obj_pos">
        <dia:point val="4.8,13.8838"/>
      </dia:attribute>
      <dia:attribute name="obj_bb">
        <dia:rectangle val="4.52881,13.6311;5.05272,15.8269"/>
      </dia:attribute>
      <dia:attribute name="conn_endpoints">
        <dia:point val="4.8,13.8838"/>
        <dia:point val="4.78153,15.5742"/>
      </dia:attribute>
      <dia:attribute name="numcp">
        <dia:int val="1"/>
      </dia:attribute>
      <dia:attribute name="line_color">
        <dia:color val="#bfbfbf"/>
      </dia:attribute>
      <dia:attribute name="line_width">
        <dia:real val="0.5"/>
      </dia:attribute>
      <dia:connections>
        <dia:connection handle="1" to="O8" connection="1"/>
      </dia:connections>
    </dia:object>
    <dia:object type="Standard - Text" version="0" id="O5">
      <dia:attribute name="obj_pos">
        <dia:point val="1.63369,2.66038"/>
      </dia:attribute>
      <dia:attribute name="obj_bb">
        <dia:rectangle val="1.63369,2.33538;8.16025,2.91819"/>
      </dia:attribute>
      <dia:attribute name="text">
        <dia:composite type="text">
          <dia:attribute name="string">
            <dia:string>#Corso UMTS/TIC C2: firewall con DMZ#</dia:string>
          </dia:attribute>
          <dia:attribute name="font">
            <dia:font family="arial" style="4" name="Helvetica-Bold"/>
          </dia:attribute>
          <dia:attribute name="height">
            <dia:real val="0.5"/>
          </dia:attribute>
          <dia:attribute name="pos">
            <dia:point val="1.63369,2.66038"/>
          </dia:attribute>
          <dia:attribute name="color">
            <dia:color val="#000000"/>
          </dia:attribute>
          <dia:attribute name="alignment">
            <dia:enum val="0"/>
          </dia:attribute>
        </dia:composite>
      </dia:attribute>
    </dia:object>
    <dia:object type="Standard - Text" version="0" id="O6">
      <dia:attribute name="obj_pos">
        <dia:point val="1.77553,3.05045"/>
      </dia:attribute>
      <dia:attribute name="obj_bb">
        <dia:rectangle val="1.77553,2.91139;6.3724,3.14654"/>
      </dia:attribute>
      <dia:attribute name="text">
        <dia:composite type="text">
          <dia:attribute name="string">
            <dia:string>#$Id: firewall-DMZ.xml,v 1.2 2005/05/30 05:31:24 doros Exp $#</dia:string>
          </dia:attribute>
          <dia:attribute name="font">
            <dia:font family="arial" style="4" name="Helvetica-Bold"/>
          </dia:attribute>
          <dia:attribute name="height">
            <dia:real val="0.20000000000000001"/>
          </dia:attribute>
          <dia:attribute name="pos">
            <dia:point val="1.77553,3.05045"/>
          </dia:attribute>
          <dia:attribute name="color">
            <dia:color val="#000000"/>
          </dia:attribute>
          <dia:attribute name="alignment">
            <dia:enum val="0"/>
          </dia:attribute>
        </dia:composite>
      </dia:attribute>
    </dia:object>
    <dia:object type="Cisco - SUN workstation" version="0" id="O7">
      <dia:attribute name="obj_pos">
        <dia:point val="10.175,7.775"/>
      </dia:attribute>
      <dia:attribute name="obj_bb">
        <dia:rectangle val="10.1074,7.06789;12.1596,9.63915"/>
      </dia:attribute>
      <dia:attribute name="elem_corner">
        <dia:point val="10.175,7.775"/>
      </dia:attribute>
      <dia:attribute name="elem_width">
        <dia:real val="1.6213710214114061"/>
      </dia:attribute>
      <dia:attribute name="elem_height">
        <dia:real val="1.3046791780942326"/>
      </dia:attribute>
      <dia:attribute name="line_width">
        <dia:real val="0.070000000000000007"/>
      </dia:attribute>
      <dia:attribute name="line_colour">
        <dia:color val="#e5e5e5"/>
      </dia:attribute>
      <dia:attribute name="fill_colour">
        <dia:color val="#000000"/>
      </dia:attribute>
      <dia:attribute name="show_background">
        <dia:boolean val="true"/>
      </dia:attribute>
      <dia:attribute name="line_style">
        <dia:enum val="0"/>
        <dia:real val="1"/>
      </dia:attribute>
      <dia:attribute name="flip_horizontal">
        <dia:boolean val="false"/>
      </dia:attribute>
      <dia:attribute name="flip_vertical">
        <dia:boolean val="false"/>
      </dia:attribute>
    </dia:object>
    <dia:object type="Cisco - SUN workstation" version="0" id="O8">
      <dia:attribute name="obj_pos">
        <dia:point val="3.9726,15.5696"/>
      </dia:attribute>
      <dia:attribute name="obj_bb">
        <dia:rectangle val="3.905,14.8625;5.95722,17.4338"/>
      </dia:attribute>
      <dia:attribute name="elem_corner">
        <dia:point val="3.9726,15.5696"/>
      </dia:attribute>
      <dia:attribute name="elem_width">
        <dia:real val="1.6213710214114061"/>
      </dia:attribute>
      <dia:attribute name="elem_height">
        <dia:real val="1.3046791780942326"/>
      </dia:attribute>
      <dia:attribute name="line_width">
        <dia:real val="0.070000000000000007"/>
      </dia:attribute>
      <dia:attribute name="line_colour">
        <dia:color val="#e5e5e5"/>
      </dia:attribute>
      <dia:attribute name="fill_colour">
        <dia:color val="#000000"/>
      </dia:attribute>
      <dia:attribute name="show_background">
        <dia:boolean val="true"/>
      </dia:attribute>
      <dia:attribute name="line_style">
        <dia:enum val="0"/>
        <dia:real val="1"/>
      </dia:attribute>
      <dia:attribute name="flip_horizontal">
        <dia:boolean val="false"/>
      </dia:attribute>
      <dia:attribute name="flip_vertical">
        <dia:boolean val="false"/>
      </dia:attribute>
    </dia:object>
    <dia:object type="Standard - Line" version="0" id="O9">
      <dia:attribute name="obj_pos">
        <dia:point val="3.3951,14.0088"/>
      </dia:attribute>
      <dia:attribute name="obj_bb">
        <dia:rectangle val="2.89459,13.5083;11.3668,14.5169"/>
      </dia:attribute>
      <dia:attribute name="conn_endpoints">
        <dia:point val="3.3951,14.0088"/>
        <dia:point val="10.8663,14.0164"/>
      </dia:attribute>
      <dia:attribute name="numcp">
        <dia:int val="1"/>
      </dia:attribute>
      <dia:attribute name="line_color">
        <dia:color val="#bfbfbf"/>
      </dia:attribute>
      <dia:attribute name="line_width">
        <dia:real val="1"/>
      </dia:attribute>
      <dia:connections>
        <dia:connection handle="0" to="O30" connection="8"/>
      </dia:connections>
    </dia:object>
    <dia:object type="Standard - Line" version="0" id="O10">
      <dia:attribute name="obj_pos">
        <dia:point val="3.0201,11.4838"/>
      </dia:attribute>
      <dia:attribute name="obj_bb">
        <dia:rectangle val="2.51774,10.9814;8.79746,12.0112"/>
      </dia:attribute>
      <dia:attribute name="conn_endpoints">
        <dia:point val="3.0201,11.4838"/>
        <dia:point val="8.2951,11.5088"/>
      </dia:attribute>
      <dia:attribute name="numcp">
        <dia:int val="1"/>
      </dia:attribute>
      <dia:attribute name="line_color">
        <dia:color val="#bfbfbf"/>
      </dia:attribute>
      <dia:attribute name="line_width">
        <dia:real val="1"/>
      </dia:attribute>
    </dia:object>
    <dia:object type="Standard - Line" version="0" id="O11">
      <dia:attribute name="obj_pos">
        <dia:point val="8.6451,5.30877"/>
      </dia:attribute>
      <dia:attribute name="obj_bb">
        <dia:rectangle val="8.14251,4.80618;9.17759,11.5776"/>
      </dia:attribute>
      <dia:attribute name="conn_endpoints">
        <dia:point val="8.6451,5.30877"/>
        <dia:point val="8.675,11.075"/>
      </dia:attribute>
      <dia:attribute name="numcp">
        <dia:int val="1"/>
      </dia:attribute>
      <dia:attribute name="line_color">
        <dia:color val="#bfbfbf"/>
      </dia:attribute>
      <dia:attribute name="line_width">
        <dia:real val="1"/>
      </dia:attribute>
    </dia:object>
    <dia:object type="Standard - Line" version="0" id="O12">
      <dia:attribute name="obj_pos">
        <dia:point val="8.625,11.9338"/>
      </dia:attribute>
      <dia:attribute name="obj_bb">
        <dia:rectangle val="8.11396,11.4314;9.12735,14.2801"/>
      </dia:attribute>
      <dia:attribute name="conn_endpoints">
        <dia:point val="8.625,11.9338"/>
        <dia:point val="8.61631,13.7777"/>
      </dia:attribute>
      <dia:attribute name="numcp">
        <dia:int val="1"/>
      </dia:attribute>
      <dia:attribute name="line_color">
        <dia:color val="#bfbfbf"/>
      </dia:attribute>
      <dia:attribute name="line_width">
        <dia:real val="1"/>
      </dia:attribute>
    </dia:object>
    <dia:object type="Standard - Text" version="0" id="O13">
      <dia:attribute name="obj_pos">
        <dia:point val="3.8701,11.6588"/>
      </dia:attribute>
      <dia:attribute name="obj_bb">
        <dia:rectangle val="3.8701,11.2088;7.9701,11.9588"/>
      </dia:attribute>
      <dia:attribute name="text">
        <dia:composite type="text">
          <dia:attribute name="string">
            <dia:string>#Rete Perimetrale#</dia:string>
          </dia:attribute>
          <dia:attribute name="font">
            <dia:font family="sans" style="0" name="Helvetica"/>
          </dia:attribute>
          <dia:attribute name="height">
            <dia:real val="0.59999999999999998"/>
          </dia:attribute>
          <dia:attribute name="pos">
            <dia:point val="3.8701,11.6588"/>
          </dia:attribute>
          <dia:attribute name="color">
            <dia:color val="#000000"/>
          </dia:attribute>
          <dia:attribute name="alignment">
            <dia:enum val="0"/>
          </dia:attribute>
        </dia:composite>
      </dia:attribute>
    </dia:object>
    <dia:object type="Cisco - IOS Firewall" version="0" id="O14">
      <dia:attribute name="obj_pos">
        <dia:point val="7.975,10.3588"/>
      </dia:attribute>
      <dia:attribute name="obj_bb">
        <dia:rectangle val="7.1003,9.44644;10.1997,13.3512"/>
      </dia:attribute>
      <dia:attribute name="elem_corner">
        <dia:point val="7.975,10.3588"/>
      </dia:attribute>
      <dia:attribute name="elem_width">
        <dia:real val="1.3039372567523597"/>
      </dia:attribute>
      <dia:attribute name="elem_height">
        <dia:real val="2.1450745128479656"/>
      </dia:attribute>
      <dia:attribute name="line_width">
        <dia:real val="0.070000000000000007"/>
      </dia:attribute>
      <dia:attribute name="line_colour">
        <dia:color val="#ffffff"/>
      </dia:attribute>
      <dia:attribute name="fill_colour">
        <dia:color val="#000000"/>
      </dia:attribute>
      <dia:attribute name="show_background">
        <dia:boolean val="true"/>
      </dia:attribute>
      <dia:attribute name="line_style">
        <dia:enum val="0"/>
        <dia:real val="1"/>
      </dia:attribute>
      <dia:attribute name="flip_horizontal">
        <dia:boolean val="false"/>
      </dia:attribute>
      <dia:attribute name="flip_vertical">
        <dia:boolean val="false"/>
      </dia:attribute>
    </dia:object>
    <dia:object type="Standard - Text" version="0" id="O15">
      <dia:attribute name="obj_pos">
        <dia:point val="2.81631,5.63538"/>
      </dia:attribute>
      <dia:attribute name="obj_bb">
        <dia:rectangle val="1.84131,5.01663;3.81006,6.82288"/>
      </dia:attribute>
      <dia:attribute name="text">
        <dia:composite type="text">
          <dia:attribute name="string">
            <dia:string>#Virtual
space#</dia:string>
          </dia:attribute>
          <dia:attribute name="font">
            <dia:font family="arial" style="4" name="Helvetica-Bold"/>
          </dia:attribute>
          <dia:attribute name="height">
            <dia:real val="0.80000000000000004"/>
          </dia:attribute>
          <dia:attribute name="pos">
            <dia:point val="2.81631,5.63538"/>
          </dia:attribute>
          <dia:attribute name="color">
            <dia:color val="#000000"/>
          </dia:attribute>
          <dia:attribute name="alignment">
            <dia:enum val="1"/>
          </dia:attribute>
        </dia:composite>
      </dia:attribute>
    </dia:object>
    <dia:object type="Standard - Text" version="0" id="O16">
      <dia:attribute name="obj_pos">
        <dia:point val="4.8701,15.2338"/>
      </dia:attribute>
      <dia:attribute name="obj_bb">
        <dia:rectangle val="3.54705,14.9945;6.20041,15.4249"/>
      </dia:attribute>
      <dia:attribute name="text">
        <dia:composite type="text">
          <dia:attribute name="string">
            <dia:string>#192.168.2.221 / eth0#</dia:string>
          </dia:attribute>
          <dia:attribute name="font">
            <dia:font family="arial" style="0" name="Helvetica"/>
          </dia:attribute>
          <dia:attribute name="height">
            <dia:real val="0.34999999999999998"/>
          </dia:attribute>
          <dia:attribute name="pos">
            <dia:point val="4.8701,15.2338"/>
          </dia:attribute>
          <dia:attribute name="color">
            <dia:color val="#000000"/>
          </dia:attribute>
          <dia:attribute name="alignment">
            <dia:enum val="1"/>
          </dia:attribute>
        </dia:composite>
      </dia:attribute>
    </dia:object>
    <dia:object type="Standard - Text" version="0" id="O17">
      <dia:attribute name="obj_pos">
        <dia:point val="4.8201,9.63377"/>
      </dia:attribute>
      <dia:attribute name="obj_bb">
        <dia:rectangle val="3.49705,9.39447;6.15041,9.82486"/>
      </dia:attribute>
      <dia:attribute name="text">
        <dia:composite type="text">
          <dia:attribute name="string">
            <dia:string>#192.168.1.222 / eth0#</dia:string>
          </dia:attribute>
          <dia:attribute name="font">
            <dia:font family="arial" style="0" name="Helvetica"/>
          </dia:attribute>
          <dia:attribute name="height">
            <dia:real val="0.34999999999999998"/>
          </dia:attribute>
          <dia:attribute name="pos">
            <dia:point val="4.8201,9.63377"/>
          </dia:attribute>
          <dia:attribute name="color">
            <dia:color val="#000000"/>
          </dia:attribute>
          <dia:attribute name="alignment">
            <dia:enum val="1"/>
          </dia:attribute>
        </dia:composite>
      </dia:attribute>
    </dia:object>
    <dia:object type="Standard - Text" version="0" id="O18">
      <dia:attribute name="obj_pos">
        <dia:point val="8.7451,8.45877"/>
      </dia:attribute>
      <dia:attribute name="obj_bb">
        <dia:rectangle val="7.34237,8.22674;10.1478,8.63533"/>
      </dia:attribute>
      <dia:attribute name="text">
        <dia:composite type="text">
          <dia:attribute name="string">
            <dia:string>#80.204.240.177 / eth0#</dia:string>
          </dia:attribute>
          <dia:attribute name="font">
            <dia:font family="arial" style="0" name="Helvetica"/>
          </dia:attribute>
          <dia:attribute name="height">
            <dia:real val="0.34999999999999998"/>
          </dia:attribute>
          <dia:attribute name="pos">
            <dia:point val="8.7451,8.45877"/>
          </dia:attribute>
          <dia:attribute name="color">
            <dia:color val="#000000"/>
          </dia:attribute>
          <dia:attribute name="alignment">
            <dia:enum val="1"/>
          </dia:attribute>
        </dia:composite>
      </dia:attribute>
    </dia:object>
    <dia:object type="Standard - Text" version="0" id="O19">
      <dia:attribute name="obj_pos">
        <dia:point val="8.6731,9.625"/>
      </dia:attribute>
      <dia:attribute name="obj_bb">
        <dia:rectangle val="7.27037,9.39297;10.0758,9.80156"/>
      </dia:attribute>
      <dia:attribute name="text">
        <dia:composite type="text">
          <dia:attribute name="string">
            <dia:string>#80.204.240.182 / eth0#</dia:string>
          </dia:attribute>
          <dia:attribute name="font">
            <dia:font family="arial" style="0" name="Helvetica"/>
          </dia:attribute>
          <dia:attribute name="height">
            <dia:real val="0.34999999999999998"/>
          </dia:attribute>
          <dia:attribute name="pos">
            <dia:point val="8.6731,9.625"/>
          </dia:attribute>
          <dia:attribute name="color">
            <dia:color val="#000000"/>
          </dia:attribute>
          <dia:attribute name="alignment">
            <dia:enum val="1"/>
          </dia:attribute>
        </dia:composite>
      </dia:attribute>
    </dia:object>
    <dia:object type="Standard - Text" version="0" id="O20">
      <dia:attribute name="obj_pos">
        <dia:point val="8.54131,12.8979"/>
      </dia:attribute>
      <dia:attribute name="obj_bb">
        <dia:rectangle val="7.25811,12.6586;9.83178,13.089"/>
      </dia:attribute>
      <dia:attribute name="text">
        <dia:composite type="text">
          <dia:attribute name="string">
            <dia:string>#192.168.2.254 /eth2#</dia:string>
          </dia:attribute>
          <dia:attribute name="font">
            <dia:font family="arial" style="0" name="Helvetica"/>
          </dia:attribute>
          <dia:attribute name="height">
            <dia:real val="0.34999999999999998"/>
          </dia:attribute>
          <dia:attribute name="pos">
            <dia:point val="8.54131,12.8979"/>
          </dia:attribute>
          <dia:attribute name="color">
            <dia:color val="#000000"/>
          </dia:attribute>
          <dia:attribute name="alignment">
            <dia:enum val="1"/>
          </dia:attribute>
        </dia:composite>
      </dia:attribute>
    </dia:object>
    <dia:object type="Standard - Text" version="0" id="O21">
      <dia:attribute name="obj_pos">
        <dia:point val="6.4951,10.9338"/>
      </dia:attribute>
      <dia:attribute name="obj_bb">
        <dia:rectangle val="5.17205,10.7018;7.81815,11.1104"/>
      </dia:attribute>
      <dia:attribute name="text">
        <dia:composite type="text">
          <dia:attribute name="string">
            <dia:string>#192.168.1.254 / eth1#</dia:string>
          </dia:attribute>
          <dia:attribute name="font">
            <dia:font family="arial" style="0" name="Helvetica"/>
          </dia:attribute>
          <dia:attribute name="height">
            <dia:real val="0.34999999999999998"/>
          </dia:attribute>
          <dia:attribute name="pos">
            <dia:point val="6.4951,10.9338"/>
          </dia:attribute>
          <dia:attribute name="color">
            <dia:color val="#000000"/>
          </dia:attribute>
          <dia:attribute name="alignment">
            <dia:enum val="1"/>
          </dia:attribute>
        </dia:composite>
      </dia:attribute>
    </dia:object>
    <dia:object type="Standard - Text" version="0" id="O22">
      <dia:attribute name="obj_pos">
        <dia:point val="11.1663,19.1914"/>
      </dia:attribute>
      <dia:attribute name="obj_bb">
        <dia:rectangle val="10.2913,18.5914;12.0413,20.3414"/>
      </dia:attribute>
      <dia:attribute name="text">
        <dia:composite type="text">
          <dia:attribute name="string">
            <dia:string>#Real
space#</dia:string>
          </dia:attribute>
          <dia:attribute name="font">
            <dia:font family="arial" style="4" name="Helvetica-Bold"/>
          </dia:attribute>
          <dia:attribute name="height">
            <dia:real val="0.80000000000000004"/>
          </dia:attribute>
          <dia:attribute name="pos">
            <dia:point val="11.1663,19.1914"/>
          </dia:attribute>
          <dia:attribute name="color">
            <dia:color val="#000000"/>
          </dia:attribute>
          <dia:attribute name="alignment">
            <dia:enum val="1"/>
          </dia:attribute>
        </dia:composite>
      </dia:attribute>
    </dia:object>
    <dia:object type="Standard - Line" version="0" id="O23">
      <dia:attribute name="obj_pos">
        <dia:point val="8.23482,16.0744"/>
      </dia:attribute>
      <dia:attribute name="obj_bb">
        <dia:rectangle val="7.95986,15.8223;8.48696,18.9749"/>
      </dia:attribute>
      <dia:attribute name="conn_endpoints">
        <dia:point val="8.23482,16.0744"/>
        <dia:point val="8.212,18.7228"/>
      </dia:attribute>
      <dia:attribute name="numcp">
        <dia:int val="1"/>
      </dia:attribute>
      <dia:attribute name="line_color">
        <dia:color val="#bfbfbf"/>
      </dia:attribute>
      <dia:attribute name="line_width">
        <dia:real val="0.5"/>
      </dia:attribute>
    </dia:object>
    <dia:object type="Cisco - WWW server" version="0" id="O24">
      <dia:attribute name="obj_pos">
        <dia:point val="4.15,7.7"/>
      </dia:attribute>
      <dia:attribute name="obj_bb">
        <dia:rectangle val="4.122,6.7;6.44553,9.71481"/>
      </dia:attribute>
      <dia:attribute name="elem_corner">
        <dia:point val="4.15,7.7"/>
      </dia:attribute>
      <dia:attribute name="elem_width">
        <dia:real val="1.4840107580235296"/>
      </dia:attribute>
      <dia:attribute name="elem_height">
        <dia:real val="1.5330292169381445"/>
      </dia:attribute>
      <dia:attribute name="line_width">
        <dia:real val="0.070000000000000007"/>
      </dia:attribute>
      <dia:attribute name="line_colour">
        <dia:color val="#e5e5e5"/>
      </dia:attribute>
      <dia:attribute name="fill_colour">
        <dia:color val="#000000"/>
      </dia:attribute>
      <dia:attribute name="show_background">
        <dia:boolean val="true"/>
      </dia:attribute>
      <dia:attribute name="line_style">
        <dia:enum val="0"/>
        <dia:real val="1"/>
      </dia:attribute>
      <dia:attribute name="flip_horizontal">
        <dia:boolean val="false"/>
      </dia:attribute>
      <dia:attribute name="flip_vertical">
        <dia:boolean val="false"/>
      </dia:attribute>
    </dia:object>
    <dia:object type="Standard - Box" version="0" id="O25">
      <dia:attribute name="obj_pos">
        <dia:point val="6.73712,18.5807"/>
      </dia:attribute>
      <dia:attribute name="obj_bb">
        <dia:rectangle val="6.71212,18.5557;9.75354,19.3471"/>
      </dia:attribute>
      <dia:attribute name="elem_corner">
        <dia:point val="6.73712,18.5807"/>
      </dia:attribute>
      <dia:attribute name="elem_width">
        <dia:real val="2.9914200000000002"/>
      </dia:attribute>
      <dia:attribute name="elem_height">
        <dia:real val="0.741421"/>
      </dia:attribute>
      <dia:attribute name="border_width">
        <dia:real val="0.050000000000000003"/>
      </dia:attribute>
      <dia:attribute name="inner_color">
        <dia:color val="#67f967"/>
      </dia:attribute>
      <dia:attribute name="show_background">
        <dia:boolean val="true"/>
      </dia:attribute>
      <dia:attribute name="corner_radius">
        <dia:real val="0.20000000000000001"/>
      </dia:attribute>
    </dia:object>
    <dia:object type="Standard - Text" version="0" id="O26">
      <dia:attribute name="obj_pos">
        <dia:point val="8.19397,18.2278"/>
      </dia:attribute>
      <dia:attribute name="obj_bb">
        <dia:rectangle val="6.951,17.9958;9.43694,18.4044"/>
      </dia:attribute>
      <dia:attribute name="text">
        <dia:composite type="text">
          <dia:attribute name="string">
            <dia:string>#192.168.77.1 / tap0#</dia:string>
          </dia:attribute>
          <dia:attribute name="font">
            <dia:font family="arial" style="0" name="Helvetica"/>
          </dia:attribute>
          <dia:attribute name="height">
            <dia:real val="0.34999999999999998"/>
          </dia:attribute>
          <dia:attribute name="pos">
            <dia:point val="8.19397,18.2278"/>
          </dia:attribute>
          <dia:attribute name="color">
            <dia:color val="#000000"/>
          </dia:attribute>
          <dia:attribute name="alignment">
            <dia:enum val="1"/>
          </dia:attribute>
        </dia:composite>
      </dia:attribute>
    </dia:object>
    <dia:object type="Standard - Text" version="0" id="O27">
      <dia:attribute name="obj_pos">
        <dia:point val="8.22943,17.1994"/>
      </dia:attribute>
      <dia:attribute name="obj_bb">
        <dia:rectangle val="6.98607,16.9674;9.47279,17.376"/>
      </dia:attribute>
      <dia:attribute name="text">
        <dia:composite type="text">
          <dia:attribute name="string">
            <dia:string>#192.168.77.2 / eth0#</dia:string>
          </dia:attribute>
          <dia:attribute name="font">
            <dia:font family="arial" style="0" name="Helvetica"/>
          </dia:attribute>
          <dia:attribute name="height">
            <dia:real val="0.34999999999999998"/>
          </dia:attribute>
          <dia:attribute name="pos">
            <dia:point val="8.22943,17.1994"/>
          </dia:attribute>
          <dia:attribute name="color">
            <dia:color val="#000000"/>
          </dia:attribute>
          <dia:attribute name="alignment">
            <dia:enum val="1"/>
          </dia:attribute>
        </dia:composite>
      </dia:attribute>
    </dia:object>
    <dia:object type="Standard - Text" version="0" id="O28">
      <dia:attribute name="obj_pos">
        <dia:point val="8.19397,19.0788"/>
      </dia:attribute>
      <dia:attribute name="obj_bb">
        <dia:rectangle val="7.41038,18.7538;8.97756,19.3366"/>
      </dia:attribute>
      <dia:attribute name="text">
        <dia:composite type="text">
          <dia:attribute name="string">
            <dia:string>#RealHost#</dia:string>
          </dia:attribute>
          <dia:attribute name="font">
            <dia:font family="arial" style="4" name="Helvetica-Bold"/>
          </dia:attribute>
          <dia:attribute name="height">
            <dia:real val="0.5"/>
          </dia:attribute>
          <dia:attribute name="pos">
            <dia:point val="8.19397,19.0788"/>
          </dia:attribute>
          <dia:attribute name="color">
            <dia:color val="#000000"/>
          </dia:attribute>
          <dia:attribute name="alignment">
            <dia:enum val="1"/>
          </dia:attribute>
        </dia:composite>
      </dia:attribute>
    </dia:object>
    <dia:object type="Standard - Ellipse" version="0" id="O29">
      <dia:attribute name="obj_pos">
        <dia:point val="8.1701,6.83877"/>
      </dia:attribute>
      <dia:attribute name="obj_bb">
        <dia:rectangle val="8.1351,6.80377;9.1801,7.74877"/>
      </dia:attribute>
      <dia:attribute name="elem_corner">
        <dia:point val="8.1701,6.83877"/>
      </dia:attribute>
      <dia:attribute name="elem_width">
        <dia:real val="0.97499999999999998"/>
      </dia:attribute>
      <dia:attribute name="elem_height">
        <dia:real val="0.875"/>
      </dia:attribute>
      <dia:attribute name="border_width">
        <dia:real val="0.070000000000000007"/>
      </dia:attribute>
      <dia:attribute name="inner_color">
        <dia:color val="#add8e6"/>
      </dia:attribute>
      <dia:attribute name="line_style">
        <dia:enum val="4"/>
      </dia:attribute>
      <dia:attribute name="dashlength">
        <dia:real val="0.5"/>
      </dia:attribute>
    </dia:object>
    <dia:object type="Standard - Ellipse" version="0" id="O30">
      <dia:attribute name="obj_pos">
        <dia:point val="2.9076,13.5713"/>
      </dia:attribute>
      <dia:attribute name="obj_bb">
        <dia:rectangle val="2.8726,13.5363;3.9176,14.4813"/>
      </dia:attribute>
      <dia:attribute name="elem_corner">
        <dia:point val="2.9076,13.5713"/>
      </dia:attribute>
      <dia:attribute name="elem_width">
        <dia:real val="0.97499999999999998"/>
      </dia:attribute>
      <dia:attribute name="elem_height">
        <dia:real val="0.875"/>
      </dia:attribute>
      <dia:attribute name="border_width">
        <dia:real val="0.070000000000000007"/>
      </dia:attribute>
      <dia:attribute name="inner_color">
        <dia:color val="#add8e6"/>
      </dia:attribute>
      <dia:attribute name="line_style">
        <dia:enum val="4"/>
      </dia:attribute>
      <dia:attribute name="dashlength">
        <dia:real val="0.5"/>
      </dia:attribute>
    </dia:object>
    <dia:object type="Standard - Ellipse" version="0" id="O31">
      <dia:attribute name="obj_pos">
        <dia:point val="2.6076,11.0713"/>
      </dia:attribute>
      <dia:attribute name="obj_bb">
        <dia:rectangle val="2.5726,11.0363;3.6176,11.9813"/>
      </dia:attribute>
      <dia:attribute name="elem_corner">
        <dia:point val="2.6076,11.0713"/>
      </dia:attribute>
      <dia:attribute name="elem_width">
        <dia:real val="0.97499999999999998"/>
      </dia:attribute>
      <dia:attribute name="elem_height">
        <dia:real val="0.875"/>
      </dia:attribute>
      <dia:attribute name="border_width">
        <dia:real val="0.070000000000000007"/>
      </dia:attribute>
      <dia:attribute name="inner_color">
        <dia:color val="#add8e6"/>
      </dia:attribute>
      <dia:attribute name="line_style">
        <dia:enum val="4"/>
      </dia:attribute>
      <dia:attribute name="dashlength">
        <dia:real val="0.5"/>
      </dia:attribute>
    </dia:object>
    <dia:object type="Standard - Text" version="0" id="O32">
      <dia:attribute name="obj_pos">
        <dia:point val="3.3701,14.1088"/>
      </dia:attribute>
      <dia:attribute name="obj_bb">
        <dia:rectangle val="3.24783,13.7838;3.49237,14.3666"/>
      </dia:attribute>
      <dia:attribute name="text">
        <dia:composite type="text">
          <dia:attribute name="string">
            <dia:string>#C#</dia:string>
          </dia:attribute>
          <dia:attribute name="font">
            <dia:font family="arial" style="4" name="Helvetica-Bold"/>
          </dia:attribute>
          <dia:attribute name="height">
            <dia:real val="0.5"/>
          </dia:attribute>
          <dia:attribute name="pos">
            <dia:point val="3.3701,14.1088"/>
          </dia:attribute>
          <dia:attribute name="color">
            <dia:color val="#000000"/>
          </dia:attribute>
          <dia:attribute name="alignment">
            <dia:enum val="1"/>
          </dia:attribute>
        </dia:composite>
      </dia:attribute>
    </dia:object>
    <dia:object type="Standard - Text" version="0" id="O33">
      <dia:attribute name="obj_pos">
        <dia:point val="8.6201,7.40877"/>
      </dia:attribute>
      <dia:attribute name="obj_bb">
        <dia:rectangle val="8.50057,7.08377;8.73963,7.66658"/>
      </dia:attribute>
      <dia:attribute name="text">
        <dia:composite type="text">
          <dia:attribute name="string">
            <dia:string>#A#</dia:string>
          </dia:attribute>
          <dia:attribute name="font">
            <dia:font family="arial" style="4" name="Helvetica-Bold"/>
          </dia:attribute>
          <dia:attribute name="height">
            <dia:real val="0.5"/>
          </dia:attribute>
          <dia:attribute name="pos">
            <dia:point val="8.6201,7.40877"/>
          </dia:attribute>
          <dia:attribute name="color">
            <dia:color val="#000000"/>
          </dia:attribute>
          <dia:attribute name="alignment">
            <dia:enum val="1"/>
          </dia:attribute>
        </dia:composite>
      </dia:attribute>
    </dia:object>
    <dia:object type="Standard - Text" version="0" id="O34">
      <dia:attribute name="obj_pos">
        <dia:point val="3.0701,11.6338"/>
      </dia:attribute>
      <dia:attribute name="obj_bb">
        <dia:rectangle val="2.95018,11.3088;3.19002,11.8916"/>
      </dia:attribute>
      <dia:attribute name="text">
        <dia:composite type="text">
          <dia:attribute name="string">
            <dia:string>#B#</dia:string>
          </dia:attribute>
          <dia:attribute name="font">
            <dia:font family="arial" style="4" name="Helvetica-Bold"/>
          </dia:attribute>
          <dia:attribute name="height">
            <dia:real val="0.5"/>
          </dia:attribute>
          <dia:attribute name="pos">
            <dia:point val="3.0701,11.6338"/>
          </dia:attribute>
          <dia:attribute name="color">
            <dia:color val="#000000"/>
          </dia:attribute>
          <dia:attribute name="alignment">
            <dia:enum val="1"/>
          </dia:attribute>
        </dia:composite>
      </dia:attribute>
    </dia:object>
    <dia:object type="Standard - Line" version="0" id="O35">
      <dia:attribute name="obj_pos">
        <dia:point val="8.22943,14.0079"/>
      </dia:attribute>
      <dia:attribute name="obj_bb">
        <dia:rectangle val="7.97889,13.7574;8.48392,16.0695"/>
      </dia:attribute>
      <dia:attribute name="conn_endpoints">
        <dia:point val="8.22943,14.0079"/>
        <dia:point val="8.23338,15.819"/>
      </dia:attribute>
      <dia:attribute name="numcp">
        <dia:int val="1"/>
      </dia:attribute>
      <dia:attribute name="line_color">
        <dia:color val="#bfbfbf"/>
      </dia:attribute>
      <dia:attribute name="line_width">
        <dia:real val="0.5"/>
      </dia:attribute>
    </dia:object>
    <dia:object type="Standard - Text" version="0" id="O36">
      <dia:attribute name="obj_pos">
        <dia:point val="7.6701,14.1588"/>
      </dia:attribute>
      <dia:attribute name="obj_bb">
        <dia:rectangle val="6.1701,13.7088;9.1701,14.4588"/>
      </dia:attribute>
      <dia:attribute name="text">
        <dia:composite type="text">
          <dia:attribute name="string">
            <dia:string>#Rete Interna#</dia:string>
          </dia:attribute>
          <dia:attribute name="font">
            <dia:font family="sans" style="0" name="Helvetica"/>
          </dia:attribute>
          <dia:attribute name="height">
            <dia:real val="0.59999999999999998"/>
          </dia:attribute>
          <dia:attribute name="pos">
            <dia:point val="7.6701,14.1588"/>
          </dia:attribute>
          <dia:attribute name="color">
            <dia:color val="#000000"/>
          </dia:attribute>
          <dia:attribute name="alignment">
            <dia:enum val="1"/>
          </dia:attribute>
        </dia:composite>
      </dia:attribute>
    </dia:object>
    <dia:object type="Cisco - WWW server" version="0" id="O37">
      <dia:attribute name="obj_pos">
        <dia:point val="7.40637,15.2856"/>
      </dia:attribute>
      <dia:attribute name="obj_bb">
        <dia:rectangle val="7.37837,14.2856;9.7019,17.3004"/>
      </dia:attribute>
      <dia:attribute name="elem_corner">
        <dia:point val="7.40637,15.2856"/>
      </dia:attribute>
      <dia:attribute name="elem_width">
        <dia:real val="1.4840107580235296"/>
      </dia:attribute>
      <dia:attribute name="elem_height">
        <dia:real val="1.5330292169381445"/>
      </dia:attribute>
      <dia:attribute name="line_width">
        <dia:real val="0.070000000000000007"/>
      </dia:attribute>
      <dia:attribute name="line_colour">
        <dia:color val="#e5e5e5"/>
      </dia:attribute>
      <dia:attribute name="fill_colour">
        <dia:color val="#000000"/>
      </dia:attribute>
      <dia:attribute name="show_background">
        <dia:boolean val="true"/>
      </dia:attribute>
      <dia:attribute name="line_style">
        <dia:enum val="0"/>
        <dia:real val="1"/>
      </dia:attribute>
      <dia:attribute name="flip_horizontal">
        <dia:boolean val="false"/>
      </dia:attribute>
      <dia:attribute name="flip_vertical">
        <dia:boolean val="false"/>
      </dia:attribute>
    </dia:object>
    <dia:object type="Standard - Text" version="0" id="O38">
      <dia:attribute name="obj_pos">
        <dia:point val="8.22943,15.0717"/>
      </dia:attribute>
      <dia:attribute name="obj_bb">
        <dia:rectangle val="6.90638,14.8324;9.55974,15.2628"/>
      </dia:attribute>
      <dia:attribute name="text">
        <dia:composite type="text">
          <dia:attribute name="string">
            <dia:string>#192.168.2.222 / eth1#</dia:string>
          </dia:attribute>
          <dia:attribute name="font">
            <dia:font family="arial" style="0" name="Helvetica"/>
          </dia:attribute>
          <dia:attribute name="height">
            <dia:real val="0.34999999999999998"/>
          </dia:attribute>
          <dia:attribute name="pos">
            <dia:point val="8.22943,15.0717"/>
          </dia:attribute>
          <dia:attribute name="color">
            <dia:color val="#000000"/>
          </dia:attribute>
          <dia:attribute name="alignment">
            <dia:enum val="1"/>
          </dia:attribute>
        </dia:composite>
      </dia:attribute>
    </dia:object>
    <dia:object type="Standard - Text" version="0" id="O39">
      <dia:attribute name="obj_pos">
        <dia:point val="9.69131,15.8664"/>
      </dia:attribute>
      <dia:attribute name="obj_bb">
        <dia:rectangle val="9.33623,15.6344;10.0464,16.043"/>
      </dia:attribute>
      <dia:attribute name="text">
        <dia:composite type="text">
          <dia:attribute name="string">
            <dia:string>#proxy#</dia:string>
          </dia:attribute>
          <dia:attribute name="font">
            <dia:font family="arial" style="0" name="Helvetica"/>
          </dia:attribute>
          <dia:attribute name="height">
            <dia:real val="0.34999999999999998"/>
          </dia:attribute>
          <dia:attribute name="pos">
            <dia:point val="9.69131,15.8664"/>
          </dia:attribute>
          <dia:attribute name="color">
            <dia:color val="#000000"/>
          </dia:attribute>
          <dia:attribute name="alignment">
            <dia:enum val="1"/>
          </dia:attribute>
        </dia:composite>
      </dia:attribute>
    </dia:object>
    <dia:object type="Standard - Text" version="0" id="O40">
      <dia:attribute name="obj_pos">
        <dia:point val="5.49131,7.36641"/>
      </dia:attribute>
      <dia:attribute name="obj_bb">
        <dia:rectangle val="4.97803,7.13438;6.00459,7.54297"/>
      </dia:attribute>
      <dia:attribute name="text">
        <dia:composite type="text">
          <dia:attribute name="string">
            <dia:string>#services#</dia:string>
          </dia:attribute>
          <dia:attribute name="font">
            <dia:font family="arial" style="0" name="Helvetica"/>
          </dia:attribute>
          <dia:attribute name="height">
            <dia:real val="0.34999999999999998"/>
          </dia:attribute>
          <dia:attribute name="pos">
            <dia:point val="5.49131,7.36641"/>
          </dia:attribute>
          <dia:attribute name="color">
            <dia:color val="#000000"/>
          </dia:attribute>
          <dia:attribute name="alignment">
            <dia:enum val="1"/>
          </dia:attribute>
        </dia:composite>
      </dia:attribute>
    </dia:object>
    <dia:object type="Standard - Text" version="0" id="O41">
      <dia:attribute name="obj_pos">
        <dia:point val="3.39131,16.0914"/>
      </dia:attribute>
      <dia:attribute name="obj_bb">
        <dia:rectangle val="3.08311,15.8594;3.69951,16.268"/>
      </dia:attribute>
      <dia:attribute name="text">
        <dia:composite type="text">
          <dia:attribute name="string">
            <dia:string>#aclnt#</dia:string>
          </dia:attribute>
          <dia:attribute name="font">
            <dia:font family="arial" style="0" name="Helvetica"/>
          </dia:attribute>
          <dia:attribute name="height">
            <dia:real val="0.34999999999999998"/>
          </dia:attribute>
          <dia:attribute name="pos">
            <dia:point val="3.39131,16.0914"/>
          </dia:attribute>
          <dia:attribute name="color">
            <dia:color val="#000000"/>
          </dia:attribute>
          <dia:attribute name="alignment">
            <dia:enum val="1"/>
          </dia:attribute>
        </dia:composite>
      </dia:attribute>
    </dia:object>
    <dia:object type="Standard - Text" version="0" id="O42">
      <dia:attribute name="obj_pos">
        <dia:point val="10.9163,7.49141"/>
      </dia:attribute>
      <dia:attribute name="obj_bb">
        <dia:rectangle val="10.287,7.25938;11.5456,7.66797"/>
      </dia:attribute>
      <dia:attribute name="text">
        <dia:composite type="text">
          <dia:attribute name="string">
            <dia:string>#router-ext#</dia:string>
          </dia:attribute>
          <dia:attribute name="font">
            <dia:font family="arial" style="0" name="Helvetica"/>
          </dia:attribute>
          <dia:attribute name="height">
            <dia:real val="0.34999999999999998"/>
          </dia:attribute>
          <dia:attribute name="pos">
            <dia:point val="10.9163,7.49141"/>
          </dia:attribute>
          <dia:attribute name="color">
            <dia:color val="#000000"/>
          </dia:attribute>
          <dia:attribute name="alignment">
            <dia:enum val="1"/>
          </dia:attribute>
        </dia:composite>
      </dia:attribute>
    </dia:object>
    <dia:object type="Network - Cloud" version="0" id="O43">
      <dia:attribute name="obj_pos">
        <dia:point val="7.255,3.07877"/>
      </dia:attribute>
      <dia:attribute name="obj_bb">
        <dia:rectangle val="7.255,3.07877;12.5884,6.06119"/>
      </dia:attribute>
      <dia:attribute name="elem_corner">
        <dia:point val="7.255,3.07877"/>
      </dia:attribute>
      <dia:attribute name="elem_width">
        <dia:real val="5.33338"/>
      </dia:attribute>
      <dia:attribute name="elem_height">
        <dia:real val="2.9824226746192615"/>
      </dia:attribute>
      <dia:attribute name="line_width">
        <dia:real val="0.070000000000000007"/>
      </dia:attribute>
      <dia:attribute name="line_colour">
        <dia:color val="#a5a3a3"/>
      </dia:attribute>
      <dia:attribute name="fill_colour">
        <dia:color val="#4d4d4d"/>
      </dia:attribute>
      <dia:attribute name="show_background">
        <dia:boolean val="true"/>
      </dia:attribute>
      <dia:attribute name="line_style">
        <dia:enum val="0"/>
        <dia:real val="1"/>
      </dia:attribute>
      <dia:attribute name="text">
        <dia:composite type="text">
          <dia:attribute name="string">
            <dia:string>#Internet#</dia:string>
          </dia:attribute>
          <dia:attribute name="font">
            <dia:font family="sans" style="0" name="Helvetica"/>
          </dia:attribute>
          <dia:attribute name="height">
            <dia:real val="0.69999999999999996"/>
          </dia:attribute>
          <dia:attribute name="pos">
            <dia:point val="10.0647,4.77256"/>
          </dia:attribute>
          <dia:attribute name="color">
            <dia:color val="#000000"/>
          </dia:attribute>
          <dia:attribute name="alignment">
            <dia:enum val="1"/>
          </dia:attribute>
        </dia:composite>
      </dia:attribute>
      <dia:attribute name="flip_horizontal">
        <dia:boolean val="false"/>
      </dia:attribute>
      <dia:attribute name="flip_vertical">
        <dia:boolean val="false"/>
      </dia:attribute>
    </dia:object>
    <dia:object type="Network - Cloud" version="0" id="O44">
      <dia:attribute name="obj_pos">
        <dia:point val="6.96381,2.925"/>
      </dia:attribute>
      <dia:attribute name="obj_bb">
        <dia:rectangle val="6.96381,2.925;12.2972,5.90742"/>
      </dia:attribute>
      <dia:attribute name="elem_corner">
        <dia:point val="6.96381,2.925"/>
      </dia:attribute>
      <dia:attribute name="elem_width">
        <dia:real val="5.33338"/>
      </dia:attribute>
      <dia:attribute name="elem_height">
        <dia:real val="2.9824226746192615"/>
      </dia:attribute>
      <dia:attribute name="line_width">
        <dia:real val="0.070000000000000007"/>
      </dia:attribute>
      <dia:attribute name="line_colour">
        <dia:color val="#a5a3a3"/>
      </dia:attribute>
      <dia:attribute name="fill_colour">
        <dia:color val="#bfbfbf"/>
      </dia:attribute>
      <dia:attribute name="show_background">
        <dia:boolean val="true"/>
      </dia:attribute>
      <dia:attribute name="line_style">
        <dia:enum val="0"/>
        <dia:real val="1"/>
      </dia:attribute>
      <dia:attribute name="text">
        <dia:composite type="text">
          <dia:attribute name="string">
            <dia:string>#Internet#</dia:string>
          </dia:attribute>
          <dia:attribute name="font">
            <dia:font family="sans" style="0" name="Helvetica"/>
          </dia:attribute>
          <dia:attribute name="height">
            <dia:real val="0.69999999999999996"/>
          </dia:attribute>
          <dia:attribute name="pos">
            <dia:point val="9.77347,4.61879"/>
          </dia:attribute>
          <dia:attribute name="color">
            <dia:color val="#000000"/>
          </dia:attribute>
          <dia:attribute name="alignment">
            <dia:enum val="1"/>
          </dia:attribute>
        </dia:composite>
      </dia:attribute>
      <dia:attribute name="flip_horizontal">
        <dia:boolean val="false"/>
      </dia:attribute>
      <dia:attribute name="flip_vertical">
        <dia:boolean val="false"/>
      </dia:attribute>
    </dia:object>
  </dia:layer>
</dia:diagram>
