<?xml version="1.0" encoding="UTF-8"?>
<dia:diagram xmlns:dia="http://www.lysator.liu.se/~alla/dia/">
  <dia:diagramdata>
    <dia:attribute name="background">
      <dia:color val="#ffffff"/>
    </dia:attribute>
    <dia:attribute name="pagebreak">
      <dia:color val="#000099"/>
    </dia:attribute>
    <dia:attribute name="paper">
      <dia:composite type="paper">
        <dia:attribute name="name">
          <dia:string>#A4#</dia:string>
        </dia:attribute>
        <dia:attribute name="tmargin">
          <dia:real val="2.8222000598907471"/>
        </dia:attribute>
        <dia:attribute name="bmargin">
          <dia:real val="2.8222000598907471"/>
        </dia:attribute>
        <dia:attribute name="lmargin">
          <dia:real val="2.8222000598907471"/>
        </dia:attribute>
        <dia:attribute name="rmargin">
          <dia:real val="2.8222000598907471"/>
        </dia:attribute>
        <dia:attribute name="is_portrait">
          <dia:boolean val="false"/>
        </dia:attribute>
        <dia:attribute name="scaling">
          <dia:real val="0.75139474868774414"/>
        </dia:attribute>
        <dia:attribute name="fitto">
          <dia:boolean val="true"/>
        </dia:attribute>
        <dia:attribute name="fitwidth">
          <dia:int val="1"/>
        </dia:attribute>
        <dia:attribute name="fitheight">
          <dia:int val="1"/>
        </dia:attribute>
      </dia:composite>
    </dia:attribute>
    <dia:attribute name="grid">
      <dia:composite type="grid">
        <dia:attribute name="width_x">
          <dia:real val="0.050000000000000003"/>
        </dia:attribute>
        <dia:attribute name="width_y">
          <dia:real val="0.050000000000000003"/>
        </dia:attribute>
        <dia:attribute name="visible_x">
          <dia:int val="1"/>
        </dia:attribute>
        <dia:attribute name="visible_y">
          <dia:int val="1"/>
        </dia:attribute>
        <dia:composite type="color"/>
      </dia:composite>
    </dia:attribute>
    <dia:attribute name="color">
      <dia:color val="#d8e5e5"/>
    </dia:attribute>
    <dia:attribute name="guides">
      <dia:composite type="guides">
        <dia:attribute name="hguides"/>
        <dia:attribute name="vguides"/>
      </dia:composite>
    </dia:attribute>
  </dia:diagramdata>
  <dia:layer name="Background" visible="true">
    <dia:object type="Standard - Box" version="0" id="O0">
      <dia:attribute name="obj_pos">
        <dia:point val="12.7827,-4.0553"/>
      </dia:attribute>
      <dia:attribute name="obj_bb">
        <dia:rectangle val="12.7627,-4.0753;19.7777,0.2647"/>
      </dia:attribute>
      <dia:attribute name="elem_corner">
        <dia:point val="12.7827,-4.0553"/>
      </dia:attribute>
      <dia:attribute name="elem_width">
        <dia:real val="6.9749999999999996"/>
      </dia:attribute>
      <dia:attribute name="elem_height">
        <dia:real val="4.2999999999999998"/>
      </dia:attribute>
      <dia:attribute name="border_width">
        <dia:real val="0.040000000000000001"/>
      </dia:attribute>
      <dia:attribute name="inner_color">
        <dia:color val="#fafaa4"/>
      </dia:attribute>
      <dia:attribute name="show_background">
        <dia:boolean val="true"/>
      </dia:attribute>
      <dia:attribute name="line_style">
        <dia:enum val="4"/>
      </dia:attribute>
      <dia:attribute name="corner_radius">
        <dia:real val="0.5"/>
      </dia:attribute>
    </dia:object>
    <dia:object type="Standard - Box" version="0" id="O1">
      <dia:attribute name="obj_pos">
        <dia:point val="6.81273,-4.06658"/>
      </dia:attribute>
      <dia:attribute name="obj_bb">
        <dia:rectangle val="6.79273,-4.08658;13.2827,9.03082"/>
      </dia:attribute>
      <dia:attribute name="elem_corner">
        <dia:point val="6.81273,-4.06658"/>
      </dia:attribute>
      <dia:attribute name="elem_width">
        <dia:real val="6.4499999999999993"/>
      </dia:attribute>
      <dia:attribute name="elem_height">
        <dia:real val="13.077400000000001"/>
      </dia:attribute>
      <dia:attribute name="border_width">
        <dia:real val="0.040000000000000001"/>
      </dia:attribute>
      <dia:attribute name="inner_color">
        <dia:color val="#fafaa4"/>
      </dia:attribute>
      <dia:attribute name="show_background">
        <dia:boolean val="true"/>
      </dia:attribute>
      <dia:attribute name="line_style">
        <dia:enum val="4"/>
      </dia:attribute>
      <dia:attribute name="corner_radius">
        <dia:real val="0.5"/>
      </dia:attribute>
    </dia:object>
    <dia:object type="Standard - Text" version="0" id="O2">
      <dia:attribute name="obj_pos">
        <dia:point val="4.45918,-10.0303"/>
      </dia:attribute>
      <dia:attribute name="obj_bb">
        <dia:rectangle val="4.45918,-10.3553;9.9709,-9.77249"/>
      </dia:attribute>
      <dia:attribute name="text">
        <dia:composite type="text">
          <dia:attribute name="string">
            <dia:string>#Sottorete per AREA/Laboratorio#</dia:string>
          </dia:attribute>
          <dia:attribute name="font">
            <dia:font family="arial" style="4" name="Helvetica-Bold"/>
          </dia:attribute>
          <dia:attribute name="height">
            <dia:real val="0.5"/>
          </dia:attribute>
          <dia:attribute name="pos">
            <dia:point val="4.45918,-10.0303"/>
          </dia:attribute>
          <dia:attribute name="color">
            <dia:color val="#000000"/>
          </dia:attribute>
          <dia:attribute name="alignment">
            <dia:enum val="0"/>
          </dia:attribute>
        </dia:composite>
      </dia:attribute>
    </dia:object>
    <dia:object type="Standard - Text" version="0" id="O3">
      <dia:attribute name="obj_pos">
        <dia:point val="4.63649,-9.67572"/>
      </dia:attribute>
      <dia:attribute name="obj_bb">
        <dia:rectangle val="4.63649,-9.81478;9.09196,-9.57963"/>
      </dia:attribute>
      <dia:attribute name="text">
        <dia:composite type="text">
          <dia:attribute name="string">
            <dia:string>#$Id: uml-RLab.xml,v 1.13 2006/03/21 06:32:25 doros Exp $#</dia:string>
          </dia:attribute>
          <dia:attribute name="font">
            <dia:font family="arial" style="4" name="Helvetica-Bold"/>
          </dia:attribute>
          <dia:attribute name="height">
            <dia:real val="0.20000000000000001"/>
          </dia:attribute>
          <dia:attribute name="pos">
            <dia:point val="4.63649,-9.67572"/>
          </dia:attribute>
          <dia:attribute name="color">
            <dia:color val="#000000"/>
          </dia:attribute>
          <dia:attribute name="alignment">
            <dia:enum val="0"/>
          </dia:attribute>
        </dia:composite>
      </dia:attribute>
    </dia:object>
    <dia:object type="Standard - Box" version="0" id="O4">
      <dia:attribute name="obj_pos">
        <dia:point val="6.81273,-8.96651"/>
      </dia:attribute>
      <dia:attribute name="obj_bb">
        <dia:rectangle val="6.78773,-8.99151;15.4877,-4.42971"/>
      </dia:attribute>
      <dia:attribute name="elem_corner">
        <dia:point val="6.81273,-8.96651"/>
      </dia:attribute>
      <dia:attribute name="elem_width">
        <dia:real val="8.6499999826225071"/>
      </dia:attribute>
      <dia:attribute name="elem_height">
        <dia:real val="4.5117967741301293"/>
      </dia:attribute>
      <dia:attribute name="border_width">
        <dia:real val="0.050000000000000003"/>
      </dia:attribute>
      <dia:attribute name="inner_color">
        <dia:color val="#caffff"/>
      </dia:attribute>
      <dia:attribute name="show_background">
        <dia:boolean val="true"/>
      </dia:attribute>
      <dia:attribute name="line_style">
        <dia:enum val="4"/>
      </dia:attribute>
      <dia:attribute name="corner_radius">
        <dia:real val="0.5"/>
      </dia:attribute>
    </dia:object>
    <dia:object type="Standard - Text" version="0" id="O5">
      <dia:attribute name="obj_pos">
        <dia:point val="12.9127,-7.9053"/>
      </dia:attribute>
      <dia:attribute name="obj_bb">
        <dia:rectangle val="12.9127,-8.5053;14.6627,-6.7553"/>
      </dia:attribute>
      <dia:attribute name="text">
        <dia:composite type="text">
          <dia:attribute name="string">
            <dia:string>#Real
space#</dia:string>
          </dia:attribute>
          <dia:attribute name="font">
            <dia:font family="arial" style="4" name="Helvetica-Bold"/>
          </dia:attribute>
          <dia:attribute name="height">
            <dia:real val="0.80000000000000004"/>
          </dia:attribute>
          <dia:attribute name="pos">
            <dia:point val="12.9127,-7.9053"/>
          </dia:attribute>
          <dia:attribute name="color">
            <dia:color val="#000000"/>
          </dia:attribute>
          <dia:attribute name="alignment">
            <dia:enum val="0"/>
          </dia:attribute>
        </dia:composite>
      </dia:attribute>
    </dia:object>
    <dia:object type="Standard - Text" version="0" id="O6">
      <dia:attribute name="obj_pos">
        <dia:point val="10.3627,2.21941"/>
      </dia:attribute>
      <dia:attribute name="obj_bb">
        <dia:rectangle val="9.90801,1.89441;10.8174,2.47722"/>
      </dia:attribute>
      <dia:attribute name="text">
        <dia:composite type="text">
          <dia:attribute name="string">
            <dia:string>#pf-a1#</dia:string>
          </dia:attribute>
          <dia:attribute name="font">
            <dia:font family="arial" style="4" name="Helvetica-Bold"/>
          </dia:attribute>
          <dia:attribute name="height">
            <dia:real val="0.5"/>
          </dia:attribute>
          <dia:attribute name="pos">
            <dia:point val="10.3627,2.21941"/>
          </dia:attribute>
          <dia:attribute name="color">
            <dia:color val="#000000"/>
          </dia:attribute>
          <dia:attribute name="alignment">
            <dia:enum val="1"/>
          </dia:attribute>
        </dia:composite>
      </dia:attribute>
    </dia:object>
    <dia:object type="Standard - Text" version="0" id="O7">
      <dia:attribute name="obj_pos">
        <dia:point val="9.00049,7.16941"/>
      </dia:attribute>
      <dia:attribute name="obj_bb">
        <dia:rectangle val="8.60713,6.84441;9.39385,7.42722"/>
      </dia:attribute>
      <dia:attribute name="text">
        <dia:composite type="text">
          <dia:attribute name="string">
            <dia:string>#a1-1#</dia:string>
          </dia:attribute>
          <dia:attribute name="font">
            <dia:font family="arial" style="4" name="Helvetica-Bold"/>
          </dia:attribute>
          <dia:attribute name="height">
            <dia:real val="0.5"/>
          </dia:attribute>
          <dia:attribute name="pos">
            <dia:point val="9.00049,7.16941"/>
          </dia:attribute>
          <dia:attribute name="color">
            <dia:color val="#000000"/>
          </dia:attribute>
          <dia:attribute name="alignment">
            <dia:enum val="1"/>
          </dia:attribute>
        </dia:composite>
      </dia:attribute>
    </dia:object>
    <dia:object type="Standard - Text" version="0" id="O8">
      <dia:attribute name="obj_pos">
        <dia:point val="7.32337,6.13929"/>
      </dia:attribute>
      <dia:attribute name="obj_bb">
        <dia:rectangle val="6.94837,5.43929;7.69837,6.63929"/>
      </dia:attribute>
      <dia:attribute name="text">
        <dia:composite type="text">
          <dia:attribute name="string">
            <dia:string>#...#</dia:string>
          </dia:attribute>
          <dia:attribute name="font">
            <dia:font family="arial" style="0" name="Helvetica"/>
          </dia:attribute>
          <dia:attribute name="height">
            <dia:real val="1"/>
          </dia:attribute>
          <dia:attribute name="pos">
            <dia:point val="7.32337,6.13929"/>
          </dia:attribute>
          <dia:attribute name="color">
            <dia:color val="#000000"/>
          </dia:attribute>
          <dia:attribute name="alignment">
            <dia:enum val="1"/>
          </dia:attribute>
        </dia:composite>
      </dia:attribute>
    </dia:object>
    <dia:object type="Standard - Text" version="0" id="O9">
      <dia:attribute name="obj_pos">
        <dia:point val="5.59394,7.23917"/>
      </dia:attribute>
      <dia:attribute name="obj_bb">
        <dia:rectangle val="4.97792,6.91417;6.20996,7.49698"/>
      </dia:attribute>
      <dia:attribute name="text">
        <dia:composite type="text">
          <dia:attribute name="string">
            <dia:string>#a1-127#</dia:string>
          </dia:attribute>
          <dia:attribute name="font">
            <dia:font family="arial" style="4" name="Helvetica-Bold"/>
          </dia:attribute>
          <dia:attribute name="height">
            <dia:real val="0.5"/>
          </dia:attribute>
          <dia:attribute name="pos">
            <dia:point val="5.59394,7.23917"/>
          </dia:attribute>
          <dia:attribute name="color">
            <dia:color val="#000000"/>
          </dia:attribute>
          <dia:attribute name="alignment">
            <dia:enum val="1"/>
          </dia:attribute>
        </dia:composite>
      </dia:attribute>
    </dia:object>
    <dia:object type="Standard - Text" version="0" id="O10">
      <dia:attribute name="obj_pos">
        <dia:point val="7.76273,-2.63059"/>
      </dia:attribute>
      <dia:attribute name="obj_bb">
        <dia:rectangle val="7.33382,-2.96579;8.20183,-2.35239"/>
      </dia:attribute>
      <dia:attribute name="text">
        <dia:composite type="text">
          <dia:attribute name="string">
            <dia:string>#www#</dia:string>
          </dia:attribute>
          <dia:attribute name="font">
            <dia:font family="arial" style="4" name="Helvetica-Bold"/>
          </dia:attribute>
          <dia:attribute name="height">
            <dia:real val="0.5"/>
          </dia:attribute>
          <dia:attribute name="pos">
            <dia:point val="7.76273,-2.63059"/>
          </dia:attribute>
          <dia:attribute name="color">
            <dia:color val="#000000"/>
          </dia:attribute>
          <dia:attribute name="alignment">
            <dia:enum val="1"/>
          </dia:attribute>
        </dia:composite>
      </dia:attribute>
    </dia:object>
    <dia:object type="Standard - Text" version="0" id="O11">
      <dia:attribute name="obj_pos">
        <dia:point val="13.7584,1.8447"/>
      </dia:attribute>
      <dia:attribute name="obj_bb">
        <dia:rectangle val="13.7584,1.2447;15.5084,2.1947"/>
      </dia:attribute>
      <dia:attribute name="text">
        <dia:composite type="text">
          <dia:attribute name="string">
            <dia:string>#Area1#</dia:string>
          </dia:attribute>
          <dia:attribute name="font">
            <dia:font family="arial" style="4" name="Helvetica-Bold"/>
          </dia:attribute>
          <dia:attribute name="height">
            <dia:real val="0.80000000000000004"/>
          </dia:attribute>
          <dia:attribute name="pos">
            <dia:point val="13.7584,1.8447"/>
          </dia:attribute>
          <dia:attribute name="color">
            <dia:color val="#000000"/>
          </dia:attribute>
          <dia:attribute name="alignment">
            <dia:enum val="0"/>
          </dia:attribute>
        </dia:composite>
      </dia:attribute>
    </dia:object>
    <dia:object type="Standard - Text" version="0" id="O12">
      <dia:attribute name="obj_pos">
        <dia:point val="18.6877,2.81941"/>
      </dia:attribute>
      <dia:attribute name="obj_bb">
        <dia:rectangle val="18.6877,2.21941;18.6877,3.16941"/>
      </dia:attribute>
      <dia:attribute name="text">
        <dia:composite type="text">
          <dia:attribute name="string">
            <dia:string>##</dia:string>
          </dia:attribute>
          <dia:attribute name="font">
            <dia:font family="sans" style="0" name="Helvetica"/>
          </dia:attribute>
          <dia:attribute name="height">
            <dia:real val="0.80000000000000004"/>
          </dia:attribute>
          <dia:attribute name="pos">
            <dia:point val="18.6877,2.81941"/>
          </dia:attribute>
          <dia:attribute name="color">
            <dia:color val="#000000"/>
          </dia:attribute>
          <dia:attribute name="alignment">
            <dia:enum val="0"/>
          </dia:attribute>
        </dia:composite>
      </dia:attribute>
    </dia:object>
    <dia:object type="Standard - Text" version="0" id="O13">
      <dia:attribute name="obj_pos">
        <dia:point val="3.96273,-4.15559"/>
      </dia:attribute>
      <dia:attribute name="obj_bb">
        <dia:rectangle val="3.96273,-4.75559;3.96273,-3.80559"/>
      </dia:attribute>
      <dia:attribute name="text">
        <dia:composite type="text">
          <dia:attribute name="string">
            <dia:string>##</dia:string>
          </dia:attribute>
          <dia:attribute name="font">
            <dia:font family="sans" style="0" name="Helvetica"/>
          </dia:attribute>
          <dia:attribute name="height">
            <dia:real val="0.80000000000000004"/>
          </dia:attribute>
          <dia:attribute name="pos">
            <dia:point val="3.96273,-4.15559"/>
          </dia:attribute>
          <dia:attribute name="color">
            <dia:color val="#000000"/>
          </dia:attribute>
          <dia:attribute name="alignment">
            <dia:enum val="0"/>
          </dia:attribute>
        </dia:composite>
      </dia:attribute>
    </dia:object>
    <dia:object type="Standard - Text" version="0" id="O14">
      <dia:attribute name="obj_pos">
        <dia:point val="18.9877,-1.00559"/>
      </dia:attribute>
      <dia:attribute name="obj_bb">
        <dia:rectangle val="18.9877,-1.60559;18.9877,-0.65559"/>
      </dia:attribute>
      <dia:attribute name="text">
        <dia:composite type="text">
          <dia:attribute name="string">
            <dia:string>##</dia:string>
          </dia:attribute>
          <dia:attribute name="font">
            <dia:font family="sans" style="0" name="Helvetica"/>
          </dia:attribute>
          <dia:attribute name="height">
            <dia:real val="0.80000000000000004"/>
          </dia:attribute>
          <dia:attribute name="pos">
            <dia:point val="18.9877,-1.00559"/>
          </dia:attribute>
          <dia:attribute name="color">
            <dia:color val="#000000"/>
          </dia:attribute>
          <dia:attribute name="alignment">
            <dia:enum val="0"/>
          </dia:attribute>
        </dia:composite>
      </dia:attribute>
    </dia:object>
    <dia:object type="Standard - Text" version="0" id="O15">
      <dia:attribute name="obj_pos">
        <dia:point val="12.6944,6.12162"/>
      </dia:attribute>
      <dia:attribute name="obj_bb">
        <dia:rectangle val="12.3194,5.42162;13.0694,6.62162"/>
      </dia:attribute>
      <dia:attribute name="text">
        <dia:composite type="text">
          <dia:attribute name="string">
            <dia:string>#...#</dia:string>
          </dia:attribute>
          <dia:attribute name="font">
            <dia:font family="arial" style="0" name="Helvetica"/>
          </dia:attribute>
          <dia:attribute name="height">
            <dia:real val="1"/>
          </dia:attribute>
          <dia:attribute name="pos">
            <dia:point val="12.6944,6.12162"/>
          </dia:attribute>
          <dia:attribute name="color">
            <dia:color val="#000000"/>
          </dia:attribute>
          <dia:attribute name="alignment">
            <dia:enum val="1"/>
          </dia:attribute>
        </dia:composite>
      </dia:attribute>
    </dia:object>
    <dia:object type="Standard - Text" version="0" id="O16">
      <dia:attribute name="obj_pos">
        <dia:point val="14.2138,7.12869"/>
      </dia:attribute>
      <dia:attribute name="obj_bb">
        <dia:rectangle val="13.5978,6.80369;14.8298,7.3865"/>
      </dia:attribute>
      <dia:attribute name="text">
        <dia:composite type="text">
          <dia:attribute name="string">
            <dia:string>#a1-191#</dia:string>
          </dia:attribute>
          <dia:attribute name="font">
            <dia:font family="arial" style="4" name="Helvetica-Bold"/>
          </dia:attribute>
          <dia:attribute name="height">
            <dia:real val="0.5"/>
          </dia:attribute>
          <dia:attribute name="pos">
            <dia:point val="14.2138,7.12869"/>
          </dia:attribute>
          <dia:attribute name="color">
            <dia:color val="#000000"/>
          </dia:attribute>
          <dia:attribute name="alignment">
            <dia:enum val="1"/>
          </dia:attribute>
        </dia:composite>
      </dia:attribute>
    </dia:object>
    <dia:object type="Standard - Line" version="0" id="O17">
      <dia:attribute name="obj_pos">
        <dia:point val="7.38773,-5.47348"/>
      </dia:attribute>
      <dia:attribute name="obj_bb">
        <dia:rectangle val="6.88773,-5.97348;13.2127,-4.97348"/>
      </dia:attribute>
      <dia:attribute name="conn_endpoints">
        <dia:point val="7.38773,-5.47348"/>
        <dia:point val="12.7127,-5.47348"/>
      </dia:attribute>
      <dia:attribute name="numcp">
        <dia:int val="1"/>
      </dia:attribute>
      <dia:attribute name="line_color">
        <dia:color val="#bfbfbf"/>
      </dia:attribute>
      <dia:attribute name="line_width">
        <dia:real val="1"/>
      </dia:attribute>
    </dia:object>
    <dia:object type="Standard - Line" version="0" id="O18">
      <dia:attribute name="obj_pos">
        <dia:point val="8.86273,2.64441"/>
      </dia:attribute>
      <dia:attribute name="obj_bb">
        <dia:rectangle val="8.58653,2.39103;9.11611,4.575"/>
      </dia:attribute>
      <dia:attribute name="conn_endpoints">
        <dia:point val="8.86273,2.64441"/>
        <dia:point val="8.83991,4.32162"/>
      </dia:attribute>
      <dia:attribute name="numcp">
        <dia:int val="1"/>
      </dia:attribute>
      <dia:attribute name="line_color">
        <dia:color val="#bfbfbf"/>
      </dia:attribute>
      <dia:attribute name="line_width">
        <dia:real val="0.5"/>
      </dia:attribute>
    </dia:object>
    <dia:object type="Standard - Line" version="0" id="O19">
      <dia:attribute name="obj_pos">
        <dia:point val="4.93773,4.24915"/>
      </dia:attribute>
      <dia:attribute name="obj_bb">
        <dia:rectangle val="4.43728,3.73977;15.2632,4.7496"/>
      </dia:attribute>
      <dia:attribute name="conn_endpoints">
        <dia:point val="4.93773,4.24915"/>
        <dia:point val="14.7627,4.24022"/>
      </dia:attribute>
      <dia:attribute name="numcp">
        <dia:int val="1"/>
      </dia:attribute>
      <dia:attribute name="line_color">
        <dia:color val="#bfbfbf"/>
      </dia:attribute>
      <dia:attribute name="line_width">
        <dia:real val="1"/>
      </dia:attribute>
    </dia:object>
    <dia:object type="Standard - Line" version="0" id="O20">
      <dia:attribute name="obj_pos">
        <dia:point val="9.77157,-7.58071"/>
      </dia:attribute>
      <dia:attribute name="obj_bb">
        <dia:rectangle val="9.51733,-7.83495;10.067,-4.91924"/>
      </dia:attribute>
      <dia:attribute name="conn_endpoints">
        <dia:point val="9.77157,-7.58071"/>
        <dia:point val="9.81273,-5.17348"/>
      </dia:attribute>
      <dia:attribute name="numcp">
        <dia:int val="1"/>
      </dia:attribute>
      <dia:attribute name="line_color">
        <dia:color val="#bfbfbf"/>
      </dia:attribute>
      <dia:attribute name="line_width">
        <dia:real val="0.5"/>
      </dia:attribute>
    </dia:object>
    <dia:object type="Standard - Ellipse" version="0" id="O21">
      <dia:attribute name="obj_pos">
        <dia:point val="8.75217,-7.71491"/>
      </dia:attribute>
      <dia:attribute name="obj_bb">
        <dia:rectangle val="8.72717,-7.73991;10.8796,-6.98991"/>
      </dia:attribute>
      <dia:attribute name="elem_corner">
        <dia:point val="8.75217,-7.71491"/>
      </dia:attribute>
      <dia:attribute name="elem_width">
        <dia:real val="2.1024699999999998"/>
      </dia:attribute>
      <dia:attribute name="elem_height">
        <dia:real val="0.69999999999999996"/>
      </dia:attribute>
      <dia:attribute name="border_width">
        <dia:real val="0.050000000000000003"/>
      </dia:attribute>
      <dia:attribute name="inner_color">
        <dia:color val="#00ff00"/>
      </dia:attribute>
    </dia:object>
    <dia:object type="Standard - Text" version="0" id="O22">
      <dia:attribute name="obj_pos">
        <dia:point val="9.8034,-7.25852"/>
      </dia:attribute>
      <dia:attribute name="obj_bb">
        <dia:rectangle val="9.06942,-7.58352;10.5374,-7.00071"/>
      </dia:attribute>
      <dia:attribute name="text">
        <dia:composite type="text">
          <dia:attribute name="string">
            <dia:string>#realHost#</dia:string>
          </dia:attribute>
          <dia:attribute name="font">
            <dia:font family="arial" style="4" name="Helvetica-Bold"/>
          </dia:attribute>
          <dia:attribute name="height">
            <dia:real val="0.5"/>
          </dia:attribute>
          <dia:attribute name="pos">
            <dia:point val="9.8034,-7.25852"/>
          </dia:attribute>
          <dia:attribute name="color">
            <dia:color val="#000000"/>
          </dia:attribute>
          <dia:attribute name="alignment">
            <dia:enum val="1"/>
          </dia:attribute>
        </dia:composite>
      </dia:attribute>
    </dia:object>
    <dia:object type="Standard - Line" version="0" id="O23">
      <dia:attribute name="obj_pos">
        <dia:point val="9.26018,-5.08255"/>
      </dia:attribute>
      <dia:attribute name="obj_bb">
        <dia:rectangle val="8.9879,-5.33473;9.51236,-2.53034"/>
      </dia:attribute>
      <dia:attribute name="conn_endpoints">
        <dia:point val="9.26018,-5.08255"/>
        <dia:point val="9.24008,-2.78252"/>
      </dia:attribute>
      <dia:attribute name="numcp">
        <dia:int val="1"/>
      </dia:attribute>
      <dia:attribute name="line_color">
        <dia:color val="#bfbfbf"/>
      </dia:attribute>
      <dia:attribute name="line_width">
        <dia:real val="0.5"/>
      </dia:attribute>
    </dia:object>
    <dia:object type="Standard - Text" version="0" id="O24">
      <dia:attribute name="obj_pos">
        <dia:point val="10.7005,7.16941"/>
      </dia:attribute>
      <dia:attribute name="obj_bb">
        <dia:rectangle val="10.0845,6.84441;11.3165,7.42722"/>
      </dia:attribute>
      <dia:attribute name="text">
        <dia:composite type="text">
          <dia:attribute name="string">
            <dia:string>#a1-129#</dia:string>
          </dia:attribute>
          <dia:attribute name="font">
            <dia:font family="arial" style="4" name="Helvetica-Bold"/>
          </dia:attribute>
          <dia:attribute name="height">
            <dia:real val="0.5"/>
          </dia:attribute>
          <dia:attribute name="pos">
            <dia:point val="10.7005,7.16941"/>
          </dia:attribute>
          <dia:attribute name="color">
            <dia:color val="#000000"/>
          </dia:attribute>
          <dia:attribute name="alignment">
            <dia:enum val="1"/>
          </dia:attribute>
        </dia:composite>
      </dia:attribute>
    </dia:object>
    <dia:object type="Standard - Line" version="0" id="O25">
      <dia:attribute name="obj_pos">
        <dia:point val="8.86273,-0.373483"/>
      </dia:attribute>
      <dia:attribute name="obj_bb">
        <dia:rectangle val="8.6125,-0.623717;9.11514,2.20654"/>
      </dia:attribute>
      <dia:attribute name="conn_endpoints">
        <dia:point val="8.86273,-0.373483"/>
        <dia:point val="8.86491,1.95631"/>
      </dia:attribute>
      <dia:attribute name="numcp">
        <dia:int val="1"/>
      </dia:attribute>
      <dia:attribute name="line_color">
        <dia:color val="#bfbfbf"/>
      </dia:attribute>
      <dia:attribute name="line_width">
        <dia:real val="0.5"/>
      </dia:attribute>
    </dia:object>
    <dia:object type="Cisco - PXF" version="0" id="O26">
      <dia:attribute name="obj_pos">
        <dia:point val="8.22174,1.34441"/>
      </dia:attribute>
      <dia:attribute name="obj_bb">
        <dia:rectangle val="8.20974,0.34441;10.6126,3.15224"/>
      </dia:attribute>
      <dia:attribute name="elem_corner">
        <dia:point val="8.22174,1.34441"/>
      </dia:attribute>
      <dia:attribute name="elem_width">
        <dia:real val="1.3909113103216306"/>
      </dia:attribute>
      <dia:attribute name="elem_height">
        <dia:real val="1.779068324011251"/>
      </dia:attribute>
      <dia:attribute name="line_width">
        <dia:real val="0.029999999999999999"/>
      </dia:attribute>
      <dia:attribute name="line_colour">
        <dia:color val="#ff0000"/>
      </dia:attribute>
      <dia:attribute name="fill_colour">
        <dia:color val="#000000"/>
      </dia:attribute>
      <dia:attribute name="show_background">
        <dia:boolean val="true"/>
      </dia:attribute>
      <dia:attribute name="line_style">
        <dia:enum val="0"/>
        <dia:real val="1"/>
      </dia:attribute>
      <dia:attribute name="flip_horizontal">
        <dia:boolean val="false"/>
      </dia:attribute>
      <dia:attribute name="flip_vertical">
        <dia:boolean val="false"/>
      </dia:attribute>
    </dia:object>
    <dia:object type="Standard - Line" version="0" id="O27">
      <dia:attribute name="obj_pos">
        <dia:point val="5.81273,4.26522"/>
      </dia:attribute>
      <dia:attribute name="obj_bb">
        <dia:rectangle val="5.56239,4.01488;6.06525,6.10665"/>
      </dia:attribute>
      <dia:attribute name="conn_endpoints">
        <dia:point val="5.81273,4.26522"/>
        <dia:point val="5.81491,5.85631"/>
      </dia:attribute>
      <dia:attribute name="numcp">
        <dia:int val="1"/>
      </dia:attribute>
      <dia:attribute name="line_color">
        <dia:color val="#bfbfbf"/>
      </dia:attribute>
      <dia:attribute name="line_width">
        <dia:real val="0.5"/>
      </dia:attribute>
    </dia:object>
    <dia:object type="Standard - Line" version="0" id="O28">
      <dia:attribute name="obj_pos">
        <dia:point val="9.13773,4.41522"/>
      </dia:attribute>
      <dia:attribute name="obj_bb">
        <dia:rectangle val="8.88713,4.16462;9.39201,6.1956"/>
      </dia:attribute>
      <dia:attribute name="conn_endpoints">
        <dia:point val="9.13773,4.41522"/>
        <dia:point val="9.14141,5.945"/>
      </dia:attribute>
      <dia:attribute name="numcp">
        <dia:int val="1"/>
      </dia:attribute>
      <dia:attribute name="line_color">
        <dia:color val="#bfbfbf"/>
      </dia:attribute>
      <dia:attribute name="line_width">
        <dia:real val="0.5"/>
      </dia:attribute>
    </dia:object>
    <dia:object type="Standard - Line" version="0" id="O29">
      <dia:attribute name="obj_pos">
        <dia:point val="10.9627,4.49022"/>
      </dia:attribute>
      <dia:attribute name="obj_bb">
        <dia:rectangle val="10.7121,4.23961;11.217,6.24561"/>
      </dia:attribute>
      <dia:attribute name="conn_endpoints">
        <dia:point val="10.9627,4.49022"/>
        <dia:point val="10.9664,5.995"/>
      </dia:attribute>
      <dia:attribute name="numcp">
        <dia:int val="1"/>
      </dia:attribute>
      <dia:attribute name="line_color">
        <dia:color val="#bfbfbf"/>
      </dia:attribute>
      <dia:attribute name="line_width">
        <dia:real val="0.5"/>
      </dia:attribute>
    </dia:object>
    <dia:object type="Standard - Line" version="0" id="O30">
      <dia:attribute name="obj_pos">
        <dia:point val="14.3627,4.31522"/>
      </dia:attribute>
      <dia:attribute name="obj_bb">
        <dia:rectangle val="14.1042,4.05674;14.6749,6.12848"/>
      </dia:attribute>
      <dia:attribute name="conn_endpoints">
        <dia:point val="14.3627,4.31522"/>
        <dia:point val="14.4164,5.87"/>
      </dia:attribute>
      <dia:attribute name="numcp">
        <dia:int val="1"/>
      </dia:attribute>
      <dia:attribute name="line_color">
        <dia:color val="#bfbfbf"/>
      </dia:attribute>
      <dia:attribute name="line_width">
        <dia:real val="0.5"/>
      </dia:attribute>
    </dia:object>
    <dia:object type="Cisco - Terminal" version="0" id="O31">
      <dia:attribute name="obj_pos">
        <dia:point val="5.07174,5.57732"/>
      </dia:attribute>
      <dia:attribute name="obj_bb">
        <dia:rectangle val="5.02346,4.87021;7.09816,7.46986"/>
      </dia:attribute>
      <dia:attribute name="elem_corner">
        <dia:point val="5.07174,5.57732"/>
      </dia:attribute>
      <dia:attribute name="elem_width">
        <dia:real val="1.3166872143020516"/>
      </dia:attribute>
      <dia:attribute name="elem_height">
        <dia:real val="1.2039725472289988"/>
      </dia:attribute>
      <dia:attribute name="line_width">
        <dia:real val="0.050000000000000003"/>
      </dia:attribute>
      <dia:attribute name="line_colour">
        <dia:color val="#f571df"/>
      </dia:attribute>
      <dia:attribute name="fill_colour">
        <dia:color val="#000000"/>
      </dia:attribute>
      <dia:attribute name="show_background">
        <dia:boolean val="true"/>
      </dia:attribute>
      <dia:attribute name="line_style">
        <dia:enum val="0"/>
        <dia:real val="1"/>
      </dia:attribute>
      <dia:attribute name="flip_horizontal">
        <dia:boolean val="false"/>
      </dia:attribute>
      <dia:attribute name="flip_vertical">
        <dia:boolean val="false"/>
      </dia:attribute>
    </dia:object>
    <dia:object type="Cisco - Terminal" version="0" id="O32">
      <dia:attribute name="obj_pos">
        <dia:point val="8.42877,5.53902"/>
      </dia:attribute>
      <dia:attribute name="obj_bb">
        <dia:rectangle val="8.38049,4.83191;10.4552,7.43156"/>
      </dia:attribute>
      <dia:attribute name="elem_corner">
        <dia:point val="8.42877,5.53902"/>
      </dia:attribute>
      <dia:attribute name="elem_width">
        <dia:real val="1.3166872143020516"/>
      </dia:attribute>
      <dia:attribute name="elem_height">
        <dia:real val="1.2039725472289988"/>
      </dia:attribute>
      <dia:attribute name="line_width">
        <dia:real val="0.050000000000000003"/>
      </dia:attribute>
      <dia:attribute name="line_colour">
        <dia:color val="#f571df"/>
      </dia:attribute>
      <dia:attribute name="fill_colour">
        <dia:color val="#000000"/>
      </dia:attribute>
      <dia:attribute name="show_background">
        <dia:boolean val="true"/>
      </dia:attribute>
      <dia:attribute name="line_style">
        <dia:enum val="0"/>
        <dia:real val="1"/>
      </dia:attribute>
      <dia:attribute name="flip_horizontal">
        <dia:boolean val="false"/>
      </dia:attribute>
      <dia:attribute name="flip_vertical">
        <dia:boolean val="false"/>
      </dia:attribute>
    </dia:object>
    <dia:object type="Standard - Text" version="0" id="O33">
      <dia:attribute name="obj_pos">
        <dia:point val="9.39051,5.20289"/>
      </dia:attribute>
      <dia:attribute name="obj_bb">
        <dia:rectangle val="9.39051,4.92476;10.5554,5.39586"/>
      </dia:attribute>
      <dia:attribute name="text">
        <dia:composite type="text">
          <dia:attribute name="string">
            <dia:string>#1 / eth0#</dia:string>
          </dia:attribute>
          <dia:attribute name="font">
            <dia:font family="arial" style="0" name="Helvetica"/>
          </dia:attribute>
          <dia:attribute name="height">
            <dia:real val="0.40000000000000002"/>
          </dia:attribute>
          <dia:attribute name="pos">
            <dia:point val="9.39051,5.20289"/>
          </dia:attribute>
          <dia:attribute name="color">
            <dia:color val="#000000"/>
          </dia:attribute>
          <dia:attribute name="alignment">
            <dia:enum val="0"/>
          </dia:attribute>
        </dia:composite>
      </dia:attribute>
    </dia:object>
    <dia:object type="Cisco - Terminal" version="0" id="O34">
      <dia:attribute name="obj_pos">
        <dia:point val="10.1847,5.49902"/>
      </dia:attribute>
      <dia:attribute name="obj_bb">
        <dia:rectangle val="10.1364,4.79191;12.2111,7.39156"/>
      </dia:attribute>
      <dia:attribute name="elem_corner">
        <dia:point val="10.1847,5.49902"/>
      </dia:attribute>
      <dia:attribute name="elem_width">
        <dia:real val="1.3166872143020516"/>
      </dia:attribute>
      <dia:attribute name="elem_height">
        <dia:real val="1.2039725472289988"/>
      </dia:attribute>
      <dia:attribute name="line_width">
        <dia:real val="0.050000000000000003"/>
      </dia:attribute>
      <dia:attribute name="line_colour">
        <dia:color val="#b20595"/>
      </dia:attribute>
      <dia:attribute name="fill_colour">
        <dia:color val="#000000"/>
      </dia:attribute>
      <dia:attribute name="show_background">
        <dia:boolean val="true"/>
      </dia:attribute>
      <dia:attribute name="line_style">
        <dia:enum val="0"/>
        <dia:real val="1"/>
      </dia:attribute>
      <dia:attribute name="flip_horizontal">
        <dia:boolean val="false"/>
      </dia:attribute>
      <dia:attribute name="flip_vertical">
        <dia:boolean val="false"/>
      </dia:attribute>
    </dia:object>
    <dia:object type="Cisco - Terminal" version="0" id="O35">
      <dia:attribute name="obj_pos">
        <dia:point val="13.6331,5.47714"/>
      </dia:attribute>
      <dia:attribute name="obj_bb">
        <dia:rectangle val="13.5848,4.77003;15.6595,7.36968"/>
      </dia:attribute>
      <dia:attribute name="elem_corner">
        <dia:point val="13.6331,5.47714"/>
      </dia:attribute>
      <dia:attribute name="elem_width">
        <dia:real val="1.3166872143020516"/>
      </dia:attribute>
      <dia:attribute name="elem_height">
        <dia:real val="1.2039725472289988"/>
      </dia:attribute>
      <dia:attribute name="line_width">
        <dia:real val="0.050000000000000003"/>
      </dia:attribute>
      <dia:attribute name="line_colour">
        <dia:color val="#b20595"/>
      </dia:attribute>
      <dia:attribute name="fill_colour">
        <dia:color val="#000000"/>
      </dia:attribute>
      <dia:attribute name="show_background">
        <dia:boolean val="true"/>
      </dia:attribute>
      <dia:attribute name="line_style">
        <dia:enum val="0"/>
        <dia:real val="1"/>
      </dia:attribute>
      <dia:attribute name="flip_horizontal">
        <dia:boolean val="false"/>
      </dia:attribute>
      <dia:attribute name="flip_vertical">
        <dia:boolean val="false"/>
      </dia:attribute>
    </dia:object>
    <dia:object type="Standard - Line" version="0" id="O36">
      <dia:attribute name="obj_pos">
        <dia:point val="9.11001,-2.84341"/>
      </dia:attribute>
      <dia:attribute name="obj_bb">
        <dia:rectangle val="8.83773,-3.09559;9.36219,-0.29121"/>
      </dia:attribute>
      <dia:attribute name="conn_endpoints">
        <dia:point val="9.11001,-2.84341"/>
        <dia:point val="9.08991,-0.543385"/>
      </dia:attribute>
      <dia:attribute name="numcp">
        <dia:int val="1"/>
      </dia:attribute>
      <dia:attribute name="line_color">
        <dia:color val="#bfbfbf"/>
      </dia:attribute>
      <dia:attribute name="line_width">
        <dia:real val="0.5"/>
      </dia:attribute>
    </dia:object>
    <dia:object type="Cisco - WWW server" version="0" id="O37">
      <dia:attribute name="obj_pos">
        <dia:point val="8.37174,-3.30559"/>
      </dia:attribute>
      <dia:attribute name="obj_bb">
        <dia:rectangle val="8.35174,-4.30559;10.6673,-1.75256"/>
      </dia:attribute>
      <dia:attribute name="elem_corner">
        <dia:point val="8.37174,-3.30559"/>
      </dia:attribute>
      <dia:attribute name="elem_width">
        <dia:real val="1.4840107580235296"/>
      </dia:attribute>
      <dia:attribute name="elem_height">
        <dia:real val="1.5330292169381445"/>
      </dia:attribute>
      <dia:attribute name="line_width">
        <dia:real val="0.050000000000000003"/>
      </dia:attribute>
      <dia:attribute name="line_colour">
        <dia:color val="#add8e6"/>
      </dia:attribute>
      <dia:attribute name="fill_colour">
        <dia:color val="#000000"/>
      </dia:attribute>
      <dia:attribute name="show_background">
        <dia:boolean val="true"/>
      </dia:attribute>
      <dia:attribute name="line_style">
        <dia:enum val="0"/>
        <dia:real val="1"/>
      </dia:attribute>
      <dia:attribute name="flip_horizontal">
        <dia:boolean val="false"/>
      </dia:attribute>
      <dia:attribute name="flip_vertical">
        <dia:boolean val="false"/>
      </dia:attribute>
    </dia:object>
    <dia:object type="Standard - Text" version="0" id="O38">
      <dia:attribute name="obj_pos">
        <dia:point val="8.26273,-1.33059"/>
      </dia:attribute>
      <dia:attribute name="obj_bb">
        <dia:rectangle val="8.26273,-1.60871;9.80882,-1.13762"/>
      </dia:attribute>
      <dia:attribute name="text">
        <dia:composite type="text">
          <dia:attribute name="string">
            <dia:string>#254 / eth1#</dia:string>
          </dia:attribute>
          <dia:attribute name="font">
            <dia:font family="arial" style="0" name="Helvetica"/>
          </dia:attribute>
          <dia:attribute name="height">
            <dia:real val="0.40000000000000002"/>
          </dia:attribute>
          <dia:attribute name="pos">
            <dia:point val="8.26273,-1.33059"/>
          </dia:attribute>
          <dia:attribute name="color">
            <dia:color val="#000000"/>
          </dia:attribute>
          <dia:attribute name="alignment">
            <dia:enum val="0"/>
          </dia:attribute>
        </dia:composite>
      </dia:attribute>
    </dia:object>
    <dia:object type="Standard - Text" version="0" id="O39">
      <dia:attribute name="obj_pos">
        <dia:point val="8.78773,0.99441"/>
      </dia:attribute>
      <dia:attribute name="obj_bb">
        <dia:rectangle val="8.78773,0.716285;10.3338,1.18738"/>
      </dia:attribute>
      <dia:attribute name="text">
        <dia:composite type="text">
          <dia:attribute name="string">
            <dia:string>#201 / eth0#</dia:string>
          </dia:attribute>
          <dia:attribute name="font">
            <dia:font family="arial" style="0" name="Helvetica"/>
          </dia:attribute>
          <dia:attribute name="height">
            <dia:real val="0.40000000000000002"/>
          </dia:attribute>
          <dia:attribute name="pos">
            <dia:point val="8.78773,0.99441"/>
          </dia:attribute>
          <dia:attribute name="color">
            <dia:color val="#000000"/>
          </dia:attribute>
          <dia:attribute name="alignment">
            <dia:enum val="0"/>
          </dia:attribute>
        </dia:composite>
      </dia:attribute>
    </dia:object>
    <dia:object type="Standard - Text" version="0" id="O40">
      <dia:attribute name="obj_pos">
        <dia:point val="9.97355,4.35483"/>
      </dia:attribute>
      <dia:attribute name="obj_bb">
        <dia:rectangle val="7.86886,4.02983;12.0782,4.61264"/>
      </dia:attribute>
      <dia:attribute name="text">
        <dia:composite type="text">
          <dia:attribute name="string">
            <dia:string>#network 192.168.1.0/24#</dia:string>
          </dia:attribute>
          <dia:attribute name="font">
            <dia:font family="arial" style="4" name="Helvetica-Bold"/>
          </dia:attribute>
          <dia:attribute name="height">
            <dia:real val="0.5"/>
          </dia:attribute>
          <dia:attribute name="pos">
            <dia:point val="9.97355,4.35483"/>
          </dia:attribute>
          <dia:attribute name="color">
            <dia:color val="#000000"/>
          </dia:attribute>
          <dia:attribute name="alignment">
            <dia:enum val="1"/>
          </dia:attribute>
        </dia:composite>
      </dia:attribute>
    </dia:object>
    <dia:object type="Standard - Text" version="0" id="O41">
      <dia:attribute name="obj_pos">
        <dia:point val="11.0377,5.14441"/>
      </dia:attribute>
      <dia:attribute name="obj_bb">
        <dia:rectangle val="11.0377,4.86628;12.5838,5.33738"/>
      </dia:attribute>
      <dia:attribute name="text">
        <dia:composite type="text">
          <dia:attribute name="string">
            <dia:string>#129 / eth0#</dia:string>
          </dia:attribute>
          <dia:attribute name="font">
            <dia:font family="arial" style="0" name="Helvetica"/>
          </dia:attribute>
          <dia:attribute name="height">
            <dia:real val="0.40000000000000002"/>
          </dia:attribute>
          <dia:attribute name="pos">
            <dia:point val="11.0377,5.14441"/>
          </dia:attribute>
          <dia:attribute name="color">
            <dia:color val="#000000"/>
          </dia:attribute>
          <dia:attribute name="alignment">
            <dia:enum val="0"/>
          </dia:attribute>
        </dia:composite>
      </dia:attribute>
    </dia:object>
    <dia:object type="Standard - Text" version="0" id="O42">
      <dia:attribute name="obj_pos">
        <dia:point val="8.91273,3.56941"/>
      </dia:attribute>
      <dia:attribute name="obj_bb">
        <dia:rectangle val="8.91273,3.29128;10.4588,3.76238"/>
      </dia:attribute>
      <dia:attribute name="text">
        <dia:composite type="text">
          <dia:attribute name="string">
            <dia:string>#254 / eth1#</dia:string>
          </dia:attribute>
          <dia:attribute name="font">
            <dia:font family="arial" style="0" name="Helvetica"/>
          </dia:attribute>
          <dia:attribute name="height">
            <dia:real val="0.40000000000000002"/>
          </dia:attribute>
          <dia:attribute name="pos">
            <dia:point val="8.91273,3.56941"/>
          </dia:attribute>
          <dia:attribute name="color">
            <dia:color val="#000000"/>
          </dia:attribute>
          <dia:attribute name="alignment">
            <dia:enum val="0"/>
          </dia:attribute>
        </dia:composite>
      </dia:attribute>
    </dia:object>
    <dia:object type="Standard - Text" version="0" id="O43">
      <dia:attribute name="obj_pos">
        <dia:point val="9.42372,-6.48424"/>
      </dia:attribute>
      <dia:attribute name="obj_bb">
        <dia:rectangle val="9.42372,-6.76236;10.5886,-6.29127"/>
      </dia:attribute>
      <dia:attribute name="text">
        <dia:composite type="text">
          <dia:attribute name="string">
            <dia:string>#1 / tap0#</dia:string>
          </dia:attribute>
          <dia:attribute name="font">
            <dia:font family="arial" style="0" name="Helvetica"/>
          </dia:attribute>
          <dia:attribute name="height">
            <dia:real val="0.40000000000000002"/>
          </dia:attribute>
          <dia:attribute name="pos">
            <dia:point val="9.42372,-6.48424"/>
          </dia:attribute>
          <dia:attribute name="color">
            <dia:color val="#000000"/>
          </dia:attribute>
          <dia:attribute name="alignment">
            <dia:enum val="0"/>
          </dia:attribute>
        </dia:composite>
      </dia:attribute>
    </dia:object>
    <dia:object type="Standard - Text" version="0" id="O44">
      <dia:attribute name="obj_pos">
        <dia:point val="10.0266,-5.38494"/>
      </dia:attribute>
      <dia:attribute name="obj_bb">
        <dia:rectangle val="7.81058,-5.70994;12.2426,-5.12713"/>
      </dia:attribute>
      <dia:attribute name="text">
        <dia:composite type="text">
          <dia:attribute name="string">
            <dia:string>#network 192.168.77.0/24#</dia:string>
          </dia:attribute>
          <dia:attribute name="font">
            <dia:font family="arial" style="0" name="Helvetica"/>
          </dia:attribute>
          <dia:attribute name="height">
            <dia:real val="0.5"/>
          </dia:attribute>
          <dia:attribute name="pos">
            <dia:point val="10.0266,-5.38494"/>
          </dia:attribute>
          <dia:attribute name="color">
            <dia:color val="#000000"/>
          </dia:attribute>
          <dia:attribute name="alignment">
            <dia:enum val="1"/>
          </dia:attribute>
        </dia:composite>
      </dia:attribute>
    </dia:object>
    <dia:object type="Standard - Text" version="0" id="O45">
      <dia:attribute name="obj_pos">
        <dia:point val="8.78543,-3.57643"/>
      </dia:attribute>
      <dia:attribute name="obj_bb">
        <dia:rectangle val="8.78543,-3.85456;9.95027,-3.38346"/>
      </dia:attribute>
      <dia:attribute name="text">
        <dia:composite type="text">
          <dia:attribute name="string">
            <dia:string>#2 / eth0#</dia:string>
          </dia:attribute>
          <dia:attribute name="font">
            <dia:font family="arial" style="0" name="Helvetica"/>
          </dia:attribute>
          <dia:attribute name="height">
            <dia:real val="0.40000000000000002"/>
          </dia:attribute>
          <dia:attribute name="pos">
            <dia:point val="8.78543,-3.57643"/>
          </dia:attribute>
          <dia:attribute name="color">
            <dia:color val="#000000"/>
          </dia:attribute>
          <dia:attribute name="alignment">
            <dia:enum val="0"/>
          </dia:attribute>
        </dia:composite>
      </dia:attribute>
    </dia:object>
    <dia:object type="Standard - Box" version="0" id="O46">
      <dia:attribute name="obj_pos">
        <dia:point val="19.1627,-4.06658"/>
      </dia:attribute>
      <dia:attribute name="obj_bb">
        <dia:rectangle val="19.1427,-4.08658;25.5327,9.03082"/>
      </dia:attribute>
      <dia:attribute name="elem_corner">
        <dia:point val="19.1627,-4.06658"/>
      </dia:attribute>
      <dia:attribute name="elem_width">
        <dia:real val="6.3500000000000014"/>
      </dia:attribute>
      <dia:attribute name="elem_height">
        <dia:real val="13.077400000000001"/>
      </dia:attribute>
      <dia:attribute name="border_width">
        <dia:real val="0.040000000000000001"/>
      </dia:attribute>
      <dia:attribute name="inner_color">
        <dia:color val="#fafaa4"/>
      </dia:attribute>
      <dia:attribute name="show_background">
        <dia:boolean val="true"/>
      </dia:attribute>
      <dia:attribute name="line_style">
        <dia:enum val="4"/>
      </dia:attribute>
      <dia:attribute name="corner_radius">
        <dia:real val="0.5"/>
      </dia:attribute>
    </dia:object>
    <dia:object type="Standard - Text" version="0" id="O47">
      <dia:attribute name="obj_pos">
        <dia:point val="15.4127,-2.7053"/>
      </dia:attribute>
      <dia:attribute name="obj_bb">
        <dia:rectangle val="15.4127,-3.3053;17.3627,-1.5553"/>
      </dia:attribute>
      <dia:attribute name="text">
        <dia:composite type="text">
          <dia:attribute name="string">
            <dia:string>#Virtual
space#</dia:string>
          </dia:attribute>
          <dia:attribute name="font">
            <dia:font family="arial" style="4" name="Helvetica-Bold"/>
          </dia:attribute>
          <dia:attribute name="height">
            <dia:real val="0.80000000000000004"/>
          </dia:attribute>
          <dia:attribute name="pos">
            <dia:point val="15.4127,-2.7053"/>
          </dia:attribute>
          <dia:attribute name="color">
            <dia:color val="#000000"/>
          </dia:attribute>
          <dia:attribute name="alignment">
            <dia:enum val="0"/>
          </dia:attribute>
        </dia:composite>
      </dia:attribute>
    </dia:object>
    <dia:object type="Standard - Text" version="0" id="O48">
      <dia:attribute name="obj_pos">
        <dia:point val="22.6184,2.21522"/>
      </dia:attribute>
      <dia:attribute name="obj_bb">
        <dia:rectangle val="22.1637,1.89022;23.0731,2.47303"/>
      </dia:attribute>
      <dia:attribute name="text">
        <dia:composite type="text">
          <dia:attribute name="string">
            <dia:string>#pf-a2#</dia:string>
          </dia:attribute>
          <dia:attribute name="font">
            <dia:font family="arial" style="4" name="Helvetica-Bold"/>
          </dia:attribute>
          <dia:attribute name="height">
            <dia:real val="0.5"/>
          </dia:attribute>
          <dia:attribute name="pos">
            <dia:point val="22.6184,2.21522"/>
          </dia:attribute>
          <dia:attribute name="color">
            <dia:color val="#000000"/>
          </dia:attribute>
          <dia:attribute name="alignment">
            <dia:enum val="1"/>
          </dia:attribute>
        </dia:composite>
      </dia:attribute>
    </dia:object>
    <dia:object type="Standard - Text" version="0" id="O49">
      <dia:attribute name="obj_pos">
        <dia:point val="21.3005,7.16941"/>
      </dia:attribute>
      <dia:attribute name="obj_bb">
        <dia:rectangle val="20.9071,6.84441;21.6939,7.42722"/>
      </dia:attribute>
      <dia:attribute name="text">
        <dia:composite type="text">
          <dia:attribute name="string">
            <dia:string>#a2-1#</dia:string>
          </dia:attribute>
          <dia:attribute name="font">
            <dia:font family="arial" style="4" name="Helvetica-Bold"/>
          </dia:attribute>
          <dia:attribute name="height">
            <dia:real val="0.5"/>
          </dia:attribute>
          <dia:attribute name="pos">
            <dia:point val="21.3005,7.16941"/>
          </dia:attribute>
          <dia:attribute name="color">
            <dia:color val="#000000"/>
          </dia:attribute>
          <dia:attribute name="alignment">
            <dia:enum val="1"/>
          </dia:attribute>
        </dia:composite>
      </dia:attribute>
    </dia:object>
    <dia:object type="Standard - Text" version="0" id="O50">
      <dia:attribute name="obj_pos">
        <dia:point val="19.6234,6.13929"/>
      </dia:attribute>
      <dia:attribute name="obj_bb">
        <dia:rectangle val="19.2484,5.43929;19.9984,6.63929"/>
      </dia:attribute>
      <dia:attribute name="text">
        <dia:composite type="text">
          <dia:attribute name="string">
            <dia:string>#...#</dia:string>
          </dia:attribute>
          <dia:attribute name="font">
            <dia:font family="arial" style="0" name="Helvetica"/>
          </dia:attribute>
          <dia:attribute name="height">
            <dia:real val="1"/>
          </dia:attribute>
          <dia:attribute name="pos">
            <dia:point val="19.6234,6.13929"/>
          </dia:attribute>
          <dia:attribute name="color">
            <dia:color val="#000000"/>
          </dia:attribute>
          <dia:attribute name="alignment">
            <dia:enum val="1"/>
          </dia:attribute>
        </dia:composite>
      </dia:attribute>
    </dia:object>
    <dia:object type="Standard - Text" version="0" id="O51">
      <dia:attribute name="obj_pos">
        <dia:point val="17.8939,7.23917"/>
      </dia:attribute>
      <dia:attribute name="obj_bb">
        <dia:rectangle val="17.2779,6.91417;18.5099,7.49698"/>
      </dia:attribute>
      <dia:attribute name="text">
        <dia:composite type="text">
          <dia:attribute name="string">
            <dia:string>#a2-127#</dia:string>
          </dia:attribute>
          <dia:attribute name="font">
            <dia:font family="arial" style="4" name="Helvetica-Bold"/>
          </dia:attribute>
          <dia:attribute name="height">
            <dia:real val="0.5"/>
          </dia:attribute>
          <dia:attribute name="pos">
            <dia:point val="17.8939,7.23917"/>
          </dia:attribute>
          <dia:attribute name="color">
            <dia:color val="#000000"/>
          </dia:attribute>
          <dia:attribute name="alignment">
            <dia:enum val="1"/>
          </dia:attribute>
        </dia:composite>
      </dia:attribute>
    </dia:object>
    <dia:object type="Standard - Text" version="0" id="O52">
      <dia:attribute name="obj_pos">
        <dia:point val="26.0934,2.01522"/>
      </dia:attribute>
      <dia:attribute name="obj_bb">
        <dia:rectangle val="26.0934,1.41522;27.8434,2.36522"/>
      </dia:attribute>
      <dia:attribute name="text">
        <dia:composite type="text">
          <dia:attribute name="string">
            <dia:string>#Area2#</dia:string>
          </dia:attribute>
          <dia:attribute name="font">
            <dia:font family="arial" style="4" name="Helvetica-Bold"/>
          </dia:attribute>
          <dia:attribute name="height">
            <dia:real val="0.80000000000000004"/>
          </dia:attribute>
          <dia:attribute name="pos">
            <dia:point val="26.0934,2.01522"/>
          </dia:attribute>
          <dia:attribute name="color">
            <dia:color val="#000000"/>
          </dia:attribute>
          <dia:attribute name="alignment">
            <dia:enum val="0"/>
          </dia:attribute>
        </dia:composite>
      </dia:attribute>
    </dia:object>
    <dia:object type="Standard - Text" version="0" id="O53">
      <dia:attribute name="obj_pos">
        <dia:point val="24.9944,6.12162"/>
      </dia:attribute>
      <dia:attribute name="obj_bb">
        <dia:rectangle val="24.6194,5.42162;25.3694,6.62162"/>
      </dia:attribute>
      <dia:attribute name="text">
        <dia:composite type="text">
          <dia:attribute name="string">
            <dia:string>#...#</dia:string>
          </dia:attribute>
          <dia:attribute name="font">
            <dia:font family="arial" style="0" name="Helvetica"/>
          </dia:attribute>
          <dia:attribute name="height">
            <dia:real val="1"/>
          </dia:attribute>
          <dia:attribute name="pos">
            <dia:point val="24.9944,6.12162"/>
          </dia:attribute>
          <dia:attribute name="color">
            <dia:color val="#000000"/>
          </dia:attribute>
          <dia:attribute name="alignment">
            <dia:enum val="1"/>
          </dia:attribute>
        </dia:composite>
      </dia:attribute>
    </dia:object>
    <dia:object type="Standard - Text" version="0" id="O54">
      <dia:attribute name="obj_pos">
        <dia:point val="26.5138,7.12869"/>
      </dia:attribute>
      <dia:attribute name="obj_bb">
        <dia:rectangle val="25.8978,6.80369;27.1298,7.3865"/>
      </dia:attribute>
      <dia:attribute name="text">
        <dia:composite type="text">
          <dia:attribute name="string">
            <dia:string>#a2-191#</dia:string>
          </dia:attribute>
          <dia:attribute name="font">
            <dia:font family="arial" style="4" name="Helvetica-Bold"/>
          </dia:attribute>
          <dia:attribute name="height">
            <dia:real val="0.5"/>
          </dia:attribute>
          <dia:attribute name="pos">
            <dia:point val="26.5138,7.12869"/>
          </dia:attribute>
          <dia:attribute name="color">
            <dia:color val="#000000"/>
          </dia:attribute>
          <dia:attribute name="alignment">
            <dia:enum val="1"/>
          </dia:attribute>
        </dia:composite>
      </dia:attribute>
    </dia:object>
    <dia:object type="Standard - Line" version="0" id="O55">
      <dia:attribute name="obj_pos">
        <dia:point val="21.1627,2.64441"/>
      </dia:attribute>
      <dia:attribute name="obj_bb">
        <dia:rectangle val="20.9118,2.39355;21.4193,4.54108"/>
      </dia:attribute>
      <dia:attribute name="conn_endpoints">
        <dia:point val="21.1627,2.64441"/>
        <dia:point val="21.1684,4.29022"/>
      </dia:attribute>
      <dia:attribute name="numcp">
        <dia:int val="1"/>
      </dia:attribute>
      <dia:attribute name="line_color">
        <dia:color val="#bfbfbf"/>
      </dia:attribute>
      <dia:attribute name="line_width">
        <dia:real val="0.5"/>
      </dia:attribute>
    </dia:object>
    <dia:object type="Standard - Line" version="0" id="O56">
      <dia:attribute name="obj_pos">
        <dia:point val="17.2494,4.43251"/>
      </dia:attribute>
      <dia:attribute name="obj_bb">
        <dia:rectangle val="16.749,3.93212;27.6188,4.94061"/>
      </dia:attribute>
      <dia:attribute name="conn_endpoints">
        <dia:point val="17.2494,4.43251"/>
        <dia:point val="27.1184,4.44022"/>
      </dia:attribute>
      <dia:attribute name="numcp">
        <dia:int val="1"/>
      </dia:attribute>
      <dia:attribute name="line_color">
        <dia:color val="#bfbfbf"/>
      </dia:attribute>
      <dia:attribute name="line_width">
        <dia:real val="1"/>
      </dia:attribute>
    </dia:object>
    <dia:object type="Standard - Text" version="0" id="O57">
      <dia:attribute name="obj_pos">
        <dia:point val="23.0005,7.16941"/>
      </dia:attribute>
      <dia:attribute name="obj_bb">
        <dia:rectangle val="22.3845,6.84441;23.6165,7.42722"/>
      </dia:attribute>
      <dia:attribute name="text">
        <dia:composite type="text">
          <dia:attribute name="string">
            <dia:string>#a2-129#</dia:string>
          </dia:attribute>
          <dia:attribute name="font">
            <dia:font family="arial" style="4" name="Helvetica-Bold"/>
          </dia:attribute>
          <dia:attribute name="height">
            <dia:real val="0.5"/>
          </dia:attribute>
          <dia:attribute name="pos">
            <dia:point val="23.0005,7.16941"/>
          </dia:attribute>
          <dia:attribute name="color">
            <dia:color val="#000000"/>
          </dia:attribute>
          <dia:attribute name="alignment">
            <dia:enum val="1"/>
          </dia:attribute>
        </dia:composite>
      </dia:attribute>
    </dia:object>
    <dia:object type="Standard - Line" version="0" id="O58">
      <dia:attribute name="obj_pos">
        <dia:point val="21.1627,-0.398483"/>
      </dia:attribute>
      <dia:attribute name="obj_bb">
        <dia:rectangle val="20.9125,-0.648716;21.4151,2.20654"/>
      </dia:attribute>
      <dia:attribute name="conn_endpoints">
        <dia:point val="21.1627,-0.398483"/>
        <dia:point val="21.1649,1.95631"/>
      </dia:attribute>
      <dia:attribute name="numcp">
        <dia:int val="1"/>
      </dia:attribute>
      <dia:attribute name="line_color">
        <dia:color val="#bfbfbf"/>
      </dia:attribute>
      <dia:attribute name="line_width">
        <dia:real val="0.5"/>
      </dia:attribute>
    </dia:object>
    <dia:object type="Cisco - PXF" version="0" id="O59">
      <dia:attribute name="obj_pos">
        <dia:point val="20.5217,1.34441"/>
      </dia:attribute>
      <dia:attribute name="obj_bb">
        <dia:rectangle val="20.5097,0.34441;22.9126,3.15224"/>
      </dia:attribute>
      <dia:attribute name="elem_corner">
        <dia:point val="20.5217,1.34441"/>
      </dia:attribute>
      <dia:attribute name="elem_width">
        <dia:real val="1.3909113103216306"/>
      </dia:attribute>
      <dia:attribute name="elem_height">
        <dia:real val="1.779068324011251"/>
      </dia:attribute>
      <dia:attribute name="line_width">
        <dia:real val="0.029999999999999999"/>
      </dia:attribute>
      <dia:attribute name="line_colour">
        <dia:color val="#ff0000"/>
      </dia:attribute>
      <dia:attribute name="fill_colour">
        <dia:color val="#000000"/>
      </dia:attribute>
      <dia:attribute name="show_background">
        <dia:boolean val="true"/>
      </dia:attribute>
      <dia:attribute name="line_style">
        <dia:enum val="0"/>
        <dia:real val="1"/>
      </dia:attribute>
      <dia:attribute name="flip_horizontal">
        <dia:boolean val="false"/>
      </dia:attribute>
      <dia:attribute name="flip_vertical">
        <dia:boolean val="false"/>
      </dia:attribute>
    </dia:object>
    <dia:object type="Standard - Line" version="0" id="O60">
      <dia:attribute name="obj_pos">
        <dia:point val="18.1184,4.31522"/>
      </dia:attribute>
      <dia:attribute name="obj_bb">
        <dia:rectangle val="17.8643,4.06465;18.369,6.10688"/>
      </dia:attribute>
      <dia:attribute name="conn_endpoints">
        <dia:point val="18.1184,4.31522"/>
        <dia:point val="18.1149,5.85631"/>
      </dia:attribute>
      <dia:attribute name="numcp">
        <dia:int val="1"/>
      </dia:attribute>
      <dia:attribute name="line_color">
        <dia:color val="#bfbfbf"/>
      </dia:attribute>
      <dia:attribute name="line_width">
        <dia:real val="0.5"/>
      </dia:attribute>
    </dia:object>
    <dia:object type="Standard - Line" version="0" id="O61">
      <dia:attribute name="obj_pos">
        <dia:point val="21.3934,4.44022"/>
      </dia:attribute>
      <dia:attribute name="obj_bb">
        <dia:rectangle val="21.1356,4.18238;21.6992,6.20284"/>
      </dia:attribute>
      <dia:attribute name="conn_endpoints">
        <dia:point val="21.3934,4.44022"/>
        <dia:point val="21.4414,5.945"/>
      </dia:attribute>
      <dia:attribute name="numcp">
        <dia:int val="1"/>
      </dia:attribute>
      <dia:attribute name="line_color">
        <dia:color val="#bfbfbf"/>
      </dia:attribute>
      <dia:attribute name="line_width">
        <dia:real val="0.5"/>
      </dia:attribute>
    </dia:object>
    <dia:object type="Standard - Line" version="0" id="O62">
      <dia:attribute name="obj_pos">
        <dia:point val="23.2184,4.41522"/>
      </dia:attribute>
      <dia:attribute name="obj_bb">
        <dia:rectangle val="22.9609,4.15774;23.5239,6.25248"/>
      </dia:attribute>
      <dia:attribute name="conn_endpoints">
        <dia:point val="23.2184,4.41522"/>
        <dia:point val="23.2664,5.995"/>
      </dia:attribute>
      <dia:attribute name="numcp">
        <dia:int val="1"/>
      </dia:attribute>
      <dia:attribute name="line_color">
        <dia:color val="#bfbfbf"/>
      </dia:attribute>
      <dia:attribute name="line_width">
        <dia:real val="0.5"/>
      </dia:attribute>
    </dia:object>
    <dia:object type="Standard - Line" version="0" id="O63">
      <dia:attribute name="obj_pos">
        <dia:point val="26.6684,4.34022"/>
      </dia:attribute>
      <dia:attribute name="obj_bb">
        <dia:rectangle val="26.4107,4.0825;26.9741,6.12772"/>
      </dia:attribute>
      <dia:attribute name="conn_endpoints">
        <dia:point val="26.6684,4.34022"/>
        <dia:point val="26.7164,5.87"/>
      </dia:attribute>
      <dia:attribute name="numcp">
        <dia:int val="1"/>
      </dia:attribute>
      <dia:attribute name="line_color">
        <dia:color val="#bfbfbf"/>
      </dia:attribute>
      <dia:attribute name="line_width">
        <dia:real val="0.5"/>
      </dia:attribute>
    </dia:object>
    <dia:object type="Cisco - Terminal" version="0" id="O64">
      <dia:attribute name="obj_pos">
        <dia:point val="17.3717,5.57732"/>
      </dia:attribute>
      <dia:attribute name="obj_bb">
        <dia:rectangle val="17.3234,4.87021;19.3981,7.46986"/>
      </dia:attribute>
      <dia:attribute name="elem_corner">
        <dia:point val="17.3717,5.57732"/>
      </dia:attribute>
      <dia:attribute name="elem_width">
        <dia:real val="1.3166872143020516"/>
      </dia:attribute>
      <dia:attribute name="elem_height">
        <dia:real val="1.2039725472289988"/>
      </dia:attribute>
      <dia:attribute name="line_width">
        <dia:real val="0.050000000000000003"/>
      </dia:attribute>
      <dia:attribute name="line_colour">
        <dia:color val="#f571df"/>
      </dia:attribute>
      <dia:attribute name="fill_colour">
        <dia:color val="#000000"/>
      </dia:attribute>
      <dia:attribute name="show_background">
        <dia:boolean val="true"/>
      </dia:attribute>
      <dia:attribute name="line_style">
        <dia:enum val="0"/>
        <dia:real val="1"/>
      </dia:attribute>
      <dia:attribute name="flip_horizontal">
        <dia:boolean val="false"/>
      </dia:attribute>
      <dia:attribute name="flip_vertical">
        <dia:boolean val="false"/>
      </dia:attribute>
    </dia:object>
    <dia:object type="Cisco - Terminal" version="0" id="O65">
      <dia:attribute name="obj_pos">
        <dia:point val="20.7288,5.53902"/>
      </dia:attribute>
      <dia:attribute name="obj_bb">
        <dia:rectangle val="20.6805,4.83191;22.7552,7.43156"/>
      </dia:attribute>
      <dia:attribute name="elem_corner">
        <dia:point val="20.7288,5.53902"/>
      </dia:attribute>
      <dia:attribute name="elem_width">
        <dia:real val="1.3166872143020516"/>
      </dia:attribute>
      <dia:attribute name="elem_height">
        <dia:real val="1.2039725472289988"/>
      </dia:attribute>
      <dia:attribute name="line_width">
        <dia:real val="0.050000000000000003"/>
      </dia:attribute>
      <dia:attribute name="line_colour">
        <dia:color val="#f571df"/>
      </dia:attribute>
      <dia:attribute name="fill_colour">
        <dia:color val="#000000"/>
      </dia:attribute>
      <dia:attribute name="show_background">
        <dia:boolean val="true"/>
      </dia:attribute>
      <dia:attribute name="line_style">
        <dia:enum val="0"/>
        <dia:real val="1"/>
      </dia:attribute>
      <dia:attribute name="flip_horizontal">
        <dia:boolean val="false"/>
      </dia:attribute>
      <dia:attribute name="flip_vertical">
        <dia:boolean val="false"/>
      </dia:attribute>
    </dia:object>
    <dia:object type="Standard - Text" version="0" id="O66">
      <dia:attribute name="obj_pos">
        <dia:point val="21.6905,5.20289"/>
      </dia:attribute>
      <dia:attribute name="obj_bb">
        <dia:rectangle val="21.6905,4.92476;22.8553,5.39586"/>
      </dia:attribute>
      <dia:attribute name="text">
        <dia:composite type="text">
          <dia:attribute name="string">
            <dia:string>#1 / eth0#</dia:string>
          </dia:attribute>
          <dia:attribute name="font">
            <dia:font family="arial" style="0" name="Helvetica"/>
          </dia:attribute>
          <dia:attribute name="height">
            <dia:real val="0.40000000000000002"/>
          </dia:attribute>
          <dia:attribute name="pos">
            <dia:point val="21.6905,5.20289"/>
          </dia:attribute>
          <dia:attribute name="color">
            <dia:color val="#000000"/>
          </dia:attribute>
          <dia:attribute name="alignment">
            <dia:enum val="0"/>
          </dia:attribute>
        </dia:composite>
      </dia:attribute>
    </dia:object>
    <dia:object type="Cisco - Terminal" version="0" id="O67">
      <dia:attribute name="obj_pos">
        <dia:point val="22.4847,5.49902"/>
      </dia:attribute>
      <dia:attribute name="obj_bb">
        <dia:rectangle val="22.4364,4.79191;24.5111,7.39156"/>
      </dia:attribute>
      <dia:attribute name="elem_corner">
        <dia:point val="22.4847,5.49902"/>
      </dia:attribute>
      <dia:attribute name="elem_width">
        <dia:real val="1.3166872143020516"/>
      </dia:attribute>
      <dia:attribute name="elem_height">
        <dia:real val="1.2039725472289988"/>
      </dia:attribute>
      <dia:attribute name="line_width">
        <dia:real val="0.050000000000000003"/>
      </dia:attribute>
      <dia:attribute name="line_colour">
        <dia:color val="#b20595"/>
      </dia:attribute>
      <dia:attribute name="fill_colour">
        <dia:color val="#000000"/>
      </dia:attribute>
      <dia:attribute name="show_background">
        <dia:boolean val="true"/>
      </dia:attribute>
      <dia:attribute name="line_style">
        <dia:enum val="0"/>
        <dia:real val="1"/>
      </dia:attribute>
      <dia:attribute name="flip_horizontal">
        <dia:boolean val="false"/>
      </dia:attribute>
      <dia:attribute name="flip_vertical">
        <dia:boolean val="false"/>
      </dia:attribute>
    </dia:object>
    <dia:object type="Cisco - Terminal" version="0" id="O68">
      <dia:attribute name="obj_pos">
        <dia:point val="25.9331,5.47714"/>
      </dia:attribute>
      <dia:attribute name="obj_bb">
        <dia:rectangle val="25.8848,4.77003;27.9595,7.36968"/>
      </dia:attribute>
      <dia:attribute name="elem_corner">
        <dia:point val="25.9331,5.47714"/>
      </dia:attribute>
      <dia:attribute name="elem_width">
        <dia:real val="1.3166872143020516"/>
      </dia:attribute>
      <dia:attribute name="elem_height">
        <dia:real val="1.2039725472289988"/>
      </dia:attribute>
      <dia:attribute name="line_width">
        <dia:real val="0.050000000000000003"/>
      </dia:attribute>
      <dia:attribute name="line_colour">
        <dia:color val="#b20595"/>
      </dia:attribute>
      <dia:attribute name="fill_colour">
        <dia:color val="#000000"/>
      </dia:attribute>
      <dia:attribute name="show_background">
        <dia:boolean val="true"/>
      </dia:attribute>
      <dia:attribute name="line_style">
        <dia:enum val="0"/>
        <dia:real val="1"/>
      </dia:attribute>
      <dia:attribute name="flip_horizontal">
        <dia:boolean val="false"/>
      </dia:attribute>
      <dia:attribute name="flip_vertical">
        <dia:boolean val="false"/>
      </dia:attribute>
    </dia:object>
    <dia:object type="Standard - Text" version="0" id="O69">
      <dia:attribute name="obj_pos">
        <dia:point val="21.0877,0.99441"/>
      </dia:attribute>
      <dia:attribute name="obj_bb">
        <dia:rectangle val="21.0877,0.716285;22.6338,1.18738"/>
      </dia:attribute>
      <dia:attribute name="text">
        <dia:composite type="text">
          <dia:attribute name="string">
            <dia:string>#202 / eth0#</dia:string>
          </dia:attribute>
          <dia:attribute name="font">
            <dia:font family="arial" style="0" name="Helvetica"/>
          </dia:attribute>
          <dia:attribute name="height">
            <dia:real val="0.40000000000000002"/>
          </dia:attribute>
          <dia:attribute name="pos">
            <dia:point val="21.0877,0.99441"/>
          </dia:attribute>
          <dia:attribute name="color">
            <dia:color val="#000000"/>
          </dia:attribute>
          <dia:attribute name="alignment">
            <dia:enum val="0"/>
          </dia:attribute>
        </dia:composite>
      </dia:attribute>
    </dia:object>
    <dia:object type="Standard - Text" version="0" id="O70">
      <dia:attribute name="obj_pos">
        <dia:point val="21.7089,4.48636"/>
      </dia:attribute>
      <dia:attribute name="obj_bb">
        <dia:rectangle val="19.6042,4.16136;23.8136,4.74417"/>
      </dia:attribute>
      <dia:attribute name="text">
        <dia:composite type="text">
          <dia:attribute name="string">
            <dia:string>#network 192.168.2.0/24#</dia:string>
          </dia:attribute>
          <dia:attribute name="font">
            <dia:font family="arial" style="4" name="Helvetica-Bold"/>
          </dia:attribute>
          <dia:attribute name="height">
            <dia:real val="0.5"/>
          </dia:attribute>
          <dia:attribute name="pos">
            <dia:point val="21.7089,4.48636"/>
          </dia:attribute>
          <dia:attribute name="color">
            <dia:color val="#000000"/>
          </dia:attribute>
          <dia:attribute name="alignment">
            <dia:enum val="1"/>
          </dia:attribute>
        </dia:composite>
      </dia:attribute>
    </dia:object>
    <dia:object type="Standard - Text" version="0" id="O71">
      <dia:attribute name="obj_pos">
        <dia:point val="23.2424,5.20511"/>
      </dia:attribute>
      <dia:attribute name="obj_bb">
        <dia:rectangle val="23.2424,4.92699;24.7885,5.39808"/>
      </dia:attribute>
      <dia:attribute name="text">
        <dia:composite type="text">
          <dia:attribute name="string">
            <dia:string>#129 / eth0#</dia:string>
          </dia:attribute>
          <dia:attribute name="font">
            <dia:font family="arial" style="0" name="Helvetica"/>
          </dia:attribute>
          <dia:attribute name="height">
            <dia:real val="0.40000000000000002"/>
          </dia:attribute>
          <dia:attribute name="pos">
            <dia:point val="23.2424,5.20511"/>
          </dia:attribute>
          <dia:attribute name="color">
            <dia:color val="#000000"/>
          </dia:attribute>
          <dia:attribute name="alignment">
            <dia:enum val="0"/>
          </dia:attribute>
        </dia:composite>
      </dia:attribute>
      <dia:connections>
        <dia:connection handle="0" to="O62" connection="0"/>
      </dia:connections>
    </dia:object>
    <dia:object type="Standard - Text" version="0" id="O72">
      <dia:attribute name="obj_pos">
        <dia:point val="21.1656,3.46731"/>
      </dia:attribute>
      <dia:attribute name="obj_bb">
        <dia:rectangle val="21.1656,3.18918;22.7117,3.66028"/>
      </dia:attribute>
      <dia:attribute name="text">
        <dia:composite type="text">
          <dia:attribute name="string">
            <dia:string>#254 / eth1#</dia:string>
          </dia:attribute>
          <dia:attribute name="font">
            <dia:font family="arial" style="0" name="Helvetica"/>
          </dia:attribute>
          <dia:attribute name="height">
            <dia:real val="0.40000000000000002"/>
          </dia:attribute>
          <dia:attribute name="pos">
            <dia:point val="21.1656,3.46731"/>
          </dia:attribute>
          <dia:attribute name="color">
            <dia:color val="#000000"/>
          </dia:attribute>
          <dia:attribute name="alignment">
            <dia:enum val="0"/>
          </dia:attribute>
        </dia:composite>
      </dia:attribute>
      <dia:connections>
        <dia:connection handle="0" to="O55" connection="0"/>
      </dia:connections>
    </dia:object>
    <dia:object type="Standard - Box" version="0" id="O73">
      <dia:attribute name="obj_pos">
        <dia:point val="12.3133,-4.00332"/>
      </dia:attribute>
      <dia:attribute name="obj_bb">
        <dia:rectangle val="12.2933,-4.02332;14.4883,0.21168"/>
      </dia:attribute>
      <dia:attribute name="elem_corner">
        <dia:point val="12.3133,-4.00332"/>
      </dia:attribute>
      <dia:attribute name="elem_width">
        <dia:real val="2.1550000000000011"/>
      </dia:attribute>
      <dia:attribute name="elem_height">
        <dia:real val="4.1949999999999994"/>
      </dia:attribute>
      <dia:attribute name="border_width">
        <dia:real val="0.040000000000000001"/>
      </dia:attribute>
      <dia:attribute name="border_color">
        <dia:color val="#fafaa4"/>
      </dia:attribute>
      <dia:attribute name="inner_color">
        <dia:color val="#fafaa4"/>
      </dia:attribute>
      <dia:attribute name="show_background">
        <dia:boolean val="true"/>
      </dia:attribute>
      <dia:attribute name="line_style">
        <dia:enum val="4"/>
      </dia:attribute>
    </dia:object>
    <dia:object type="Standard - Box" version="0" id="O74">
      <dia:attribute name="obj_pos">
        <dia:point val="18.0133,-3.98332"/>
      </dia:attribute>
      <dia:attribute name="obj_bb">
        <dia:rectangle val="17.9933,-4.00332;20.1883,0.23168"/>
      </dia:attribute>
      <dia:attribute name="elem_corner">
        <dia:point val="18.0133,-3.98332"/>
      </dia:attribute>
      <dia:attribute name="elem_width">
        <dia:real val="2.1550000000000011"/>
      </dia:attribute>
      <dia:attribute name="elem_height">
        <dia:real val="4.1949999999999994"/>
      </dia:attribute>
      <dia:attribute name="border_width">
        <dia:real val="0.040000000000000001"/>
      </dia:attribute>
      <dia:attribute name="border_color">
        <dia:color val="#fafaa4"/>
      </dia:attribute>
      <dia:attribute name="inner_color">
        <dia:color val="#fafaa4"/>
      </dia:attribute>
      <dia:attribute name="show_background">
        <dia:boolean val="true"/>
      </dia:attribute>
      <dia:attribute name="line_style">
        <dia:enum val="4"/>
      </dia:attribute>
    </dia:object>
    <dia:object type="Standard - Line" version="0" id="O75">
      <dia:attribute name="obj_pos">
        <dia:point val="7.66273,-0.648483"/>
      </dia:attribute>
      <dia:attribute name="obj_bb">
        <dia:rectangle val="7.16253,-1.1555;24.9629,-0.14828"/>
      </dia:attribute>
      <dia:attribute name="conn_endpoints">
        <dia:point val="7.66273,-0.648483"/>
        <dia:point val="24.4627,-0.6553"/>
      </dia:attribute>
      <dia:attribute name="numcp">
        <dia:int val="1"/>
      </dia:attribute>
      <dia:attribute name="line_color">
        <dia:color val="#bfbfbf"/>
      </dia:attribute>
      <dia:attribute name="line_width">
        <dia:real val="1"/>
      </dia:attribute>
    </dia:object>
    <dia:object type="Standard - Text" version="0" id="O76">
      <dia:attribute name="obj_pos">
        <dia:point val="16.3127,-0.6053"/>
      </dia:attribute>
      <dia:attribute name="obj_bb">
        <dia:rectangle val="13.058,-0.940495;19.5776,-0.327097"/>
      </dia:attribute>
      <dia:attribute name="text">
        <dia:composite type="text">
          <dia:attribute name="string">
            <dia:string>#BACKBONE - network 192.168.0.0/24#</dia:string>
          </dia:attribute>
          <dia:attribute name="font">
            <dia:font family="arial" style="0" name="Helvetica"/>
          </dia:attribute>
          <dia:attribute name="height">
            <dia:real val="0.5"/>
          </dia:attribute>
          <dia:attribute name="pos">
            <dia:point val="16.3127,-0.6053"/>
          </dia:attribute>
          <dia:attribute name="color">
            <dia:color val="#000000"/>
          </dia:attribute>
          <dia:attribute name="alignment">
            <dia:enum val="1"/>
          </dia:attribute>
        </dia:composite>
      </dia:attribute>
    </dia:object>
    <dia:object type="Standard - Text" version="0" id="O77">
      <dia:attribute name="obj_pos">
        <dia:point val="28.4683,-0.353324"/>
      </dia:attribute>
      <dia:attribute name="obj_bb">
        <dia:rectangle val="28.4683,-0.953324;28.4683,-0.003324"/>
      </dia:attribute>
      <dia:attribute name="text">
        <dia:composite type="text">
          <dia:attribute name="string">
            <dia:string>##</dia:string>
          </dia:attribute>
          <dia:attribute name="font">
            <dia:font family="sans" style="0" name="Helvetica"/>
          </dia:attribute>
          <dia:attribute name="height">
            <dia:real val="0.80000000000000004"/>
          </dia:attribute>
          <dia:attribute name="pos">
            <dia:point val="28.4683,-0.353324"/>
          </dia:attribute>
          <dia:attribute name="color">
            <dia:color val="#000000"/>
          </dia:attribute>
          <dia:attribute name="alignment">
            <dia:enum val="0"/>
          </dia:attribute>
        </dia:composite>
      </dia:attribute>
    </dia:object>
    <dia:object type="Standard - Text" version="0" id="O78">
      <dia:attribute name="obj_pos">
        <dia:point val="16.0127,9.73083"/>
      </dia:attribute>
      <dia:attribute name="obj_bb">
        <dia:rectangle val="16.0127,9.13083;16.0127,10.0808"/>
      </dia:attribute>
      <dia:attribute name="text">
        <dia:composite type="text">
          <dia:attribute name="string">
            <dia:string>##</dia:string>
          </dia:attribute>
          <dia:attribute name="font">
            <dia:font family="sans" style="0" name="Helvetica"/>
          </dia:attribute>
          <dia:attribute name="height">
            <dia:real val="0.80000000000000004"/>
          </dia:attribute>
          <dia:attribute name="pos">
            <dia:point val="16.0127,9.73083"/>
          </dia:attribute>
          <dia:attribute name="color">
            <dia:color val="#000000"/>
          </dia:attribute>
          <dia:attribute name="alignment">
            <dia:enum val="0"/>
          </dia:attribute>
        </dia:composite>
      </dia:attribute>
    </dia:object>
    <dia:object type="Standard - Box" version="0" id="O79">
      <dia:attribute name="obj_pos">
        <dia:point val="16.4877,0.46941"/>
      </dia:attribute>
      <dia:attribute name="obj_bb">
        <dia:rectangle val="16.4677,0.44941;28.3327,7.67475"/>
      </dia:attribute>
      <dia:attribute name="elem_corner">
        <dia:point val="16.4877,0.46941"/>
      </dia:attribute>
      <dia:attribute name="elem_width">
        <dia:real val="11.825000000000005"/>
      </dia:attribute>
      <dia:attribute name="elem_height">
        <dia:real val="7.1853400000000001"/>
      </dia:attribute>
      <dia:attribute name="border_width">
        <dia:real val="0.040000000000000001"/>
      </dia:attribute>
      <dia:attribute name="inner_color">
        <dia:color val="#ecffd0"/>
      </dia:attribute>
      <dia:attribute name="show_background">
        <dia:boolean val="false"/>
      </dia:attribute>
      <dia:attribute name="line_style">
        <dia:enum val="4"/>
      </dia:attribute>
      <dia:attribute name="corner_radius">
        <dia:real val="0.5"/>
      </dia:attribute>
    </dia:object>
    <dia:object type="Standard - Box" version="0" id="O80">
      <dia:attribute name="obj_pos">
        <dia:point val="4.18773,0.46941"/>
      </dia:attribute>
      <dia:attribute name="obj_bb">
        <dia:rectangle val="4.16773,0.44941;16.0327,7.67475"/>
      </dia:attribute>
      <dia:attribute name="elem_corner">
        <dia:point val="4.18773,0.46941"/>
      </dia:attribute>
      <dia:attribute name="elem_width">
        <dia:real val="11.825000000000005"/>
      </dia:attribute>
      <dia:attribute name="elem_height">
        <dia:real val="7.1853400000000001"/>
      </dia:attribute>
      <dia:attribute name="border_width">
        <dia:real val="0.040000000000000001"/>
      </dia:attribute>
      <dia:attribute name="inner_color">
        <dia:color val="#ecffd0"/>
      </dia:attribute>
      <dia:attribute name="show_background">
        <dia:boolean val="false"/>
      </dia:attribute>
      <dia:attribute name="line_style">
        <dia:enum val="4"/>
      </dia:attribute>
      <dia:attribute name="corner_radius">
        <dia:real val="0.5"/>
      </dia:attribute>
    </dia:object>
  </dia:layer>
</dia:diagram>
